{"type":"FeatureCollection", "features": [
{"type":"Feature","geometry":{"type":"Point","coordinates":[2.944095000000061,50.85028200000005,0,-1.7976931348623157e+308]},"properties":{"Name":"50th ID","FolderPath":"1944-12-27T00:00:01Z","SymbolID":0,"AltMode":-1,"Base":0,"TimeSpan":0,"TimeStamp":0,"BeginTime":"","EndTime":"","Snippet":"","PopupInfo":"","HasLabel":-1,"LabelID":0}},
{"type":"Feature","geometry":{"type":"Point","coordinates":[4.802176000000031,51.566095000000075,0,-1.7976931348623157e+308]},"properties":{"Name":"4th AD (CDN)","FolderPath":"1944-12-27T00:00:01Z","SymbolID":1,"AltMode":-1,"Base":0,"TimeSpan":0,"TimeStamp":0,"BeginTime":"","EndTime":"","Snippet":"","PopupInfo":"","HasLabel":-1,"LabelID":0}},
{"type":"Feature","geometry":{"type":"Point","coordinates":[5.204545000000053,51.70213700000005,0,-1.7976931348623157e+308]},"properties":{"Name":"POL AD","FolderPath":"1944-12-27T00:00:01Z","SymbolID":2,"AltMode":-1,"Base":0,"TimeSpan":0,"TimeStamp":0,"BeginTime":"","EndTime":"","Snippet":"","PopupInfo":"","HasLabel":-1,"LabelID":0}},
{"type":"Feature","geometry":{"type":"Point","coordinates":[5.791870000000074,51.88737800000007,0,-1.7976931348623157e+308]},"properties":{"Name":"49th ID","FolderPath":"1944-12-27T00:00:01Z","SymbolID":0,"AltMode":-1,"Base":0,"TimeSpan":0,"TimeStamp":0,"BeginTime":"","EndTime":"","Snippet":"","PopupInfo":"","HasLabel":-1,"LabelID":0}},
{"type":"Feature","geometry":{"type":"Point","coordinates":[5.83756900000003,51.83904300000006,0,-1.7976931348623157e+308]},"properties":{"Name":"3rd ID (CDN)","FolderPath":"1944-12-27T00:00:01Z","SymbolID":3,"AltMode":-1,"Base":0,"TimeSpan":0,"TimeStamp":0,"BeginTime":"","EndTime":"","Snippet":"","PopupInfo":"","HasLabel":-1,"LabelID":0}},
{"type":"Feature","geometry":{"type":"Point","coordinates":[5.874687000000051,51.777792000000034,0,-1.7976931348623157e+308]},"properties":{"Name":"2nd ID (CDN)","FolderPath":"1944-12-27T00:00:01Z","SymbolID":3,"AltMode":-1,"Base":0,"TimeSpan":0,"TimeStamp":0,"BeginTime":"","EndTime":"","Snippet":"","PopupInfo":"","HasLabel":-1,"LabelID":0}},
{"type":"Feature","geometry":{"type":"Point","coordinates":[6.011278000000061,51.49326400000007,0,-1.7976931348623157e+308]},"properties":{"Name":"3rd ID","FolderPath":"1944-12-27T00:00:01Z","SymbolID":0,"AltMode":-1,"Base":0,"TimeSpan":0,"TimeStamp":0,"BeginTime":"","EndTime":"","Snippet":"","PopupInfo":"","HasLabel":-1,"LabelID":0}},
{"type":"Feature","geometry":{"type":"Point","coordinates":[5.984915000000058,51.34775700000006,0,-1.7976931348623157e+308]},"properties":{"Name":"15th ID","FolderPath":"1944-12-27T00:00:01Z","SymbolID":0,"AltMode":-1,"Base":0,"TimeSpan":0,"TimeStamp":0,"BeginTime":"","EndTime":"","Snippet":"","PopupInfo":"","HasLabel":-1,"LabelID":0}},
{"type":"Feature","geometry":{"type":"Point","coordinates":[5.845046000000025,51.22948300000007,0,-1.7976931348623157e+308]},"properties":{"Name":"11th AD","FolderPath":"1944-12-27T00:00:01Z","SymbolID":4,"AltMode":-1,"Base":0,"TimeSpan":0,"TimeStamp":0,"BeginTime":"","EndTime":"","Snippet":"","PopupInfo":"","HasLabel":-1,"LabelID":0}},
{"type":"Feature","geometry":{"type":"Point","coordinates":[4.6049260000000345,50.75797000000006,0,-1.7976931348623157e+308]},"properties":{"Name":"53rd ID","FolderPath":"1944-12-27T00:00:01Z","SymbolID":0,"AltMode":-1,"Base":0,"TimeSpan":0,"TimeStamp":0,"BeginTime":"","EndTime":"","Snippet":"","PopupInfo":"","HasLabel":-1,"LabelID":0}},
{"type":"Feature","geometry":{"type":"Point","coordinates":[5.085975000000076,50.77548800000005,0,-1.7976931348623157e+308]},"properties":{"Name":"GDS AD","FolderPath":"1944-12-27T00:00:01Z","SymbolID":4,"AltMode":-1,"Base":0,"TimeSpan":0,"TimeStamp":0,"BeginTime":"","EndTime":"","Snippet":"","PopupInfo":"","HasLabel":-1,"LabelID":0}},
{"type":"Feature","geometry":{"type":"Point","coordinates":[5.397740000000056,50.87767800000006,0,-1.7976931348623157e+308]},"properties":{"Name":"43rd ID","FolderPath":"1944-12-27T00:00:01Z","SymbolID":0,"AltMode":-1,"Base":0,"TimeSpan":0,"TimeStamp":0,"BeginTime":"","EndTime":"","Snippet":"","PopupInfo":"","HasLabel":-1,"LabelID":0}},
{"type":"Feature","geometry":{"type":"Point","coordinates":[5.8311010000000465,51.00884800000006,0,-1.7976931348623157e+308]},"properties":{"Name":"7th AD","FolderPath":"1944-12-27T00:00:01Z","SymbolID":4,"AltMode":-1,"Base":0,"TimeSpan":0,"TimeStamp":0,"BeginTime":"","EndTime":"","Snippet":"","PopupInfo":"","HasLabel":-1,"LabelID":0}},
{"type":"Feature","geometry":{"type":"Point","coordinates":[6.032731000000069,50.96906400000006,0,-1.7976931348623157e+308]},"properties":{"Name":"52nd ID","FolderPath":"1944-12-27T00:00:01Z","SymbolID":0,"AltMode":-1,"Base":0,"TimeSpan":0,"TimeStamp":0,"BeginTime":"","EndTime":"","Snippet":"","PopupInfo":"","HasLabel":-1,"LabelID":0}},
{"type":"Feature","geometry":{"type":"Point","coordinates":[6.158065000000022,50.94175700000005,0,-1.7976931348623157e+308]},"properties":{"Name":"102nd ID","FolderPath":"1944-12-27T00:00:01Z","SymbolID":5,"AltMode":-1,"Base":0,"TimeSpan":0,"TimeStamp":0,"BeginTime":"","EndTime":"","Snippet":"","PopupInfo":"","HasLabel":-1,"LabelID":0}},
{"type":"Feature","geometry":{"type":"Point","coordinates":[6.261235000000056,50.89108600000003,0,-1.7976931348623157e+308]},"properties":{"Name":"29th ID","FolderPath":"1944-12-27T00:00:01Z","SymbolID":5,"AltMode":-1,"Base":0,"TimeSpan":0,"TimeStamp":0,"BeginTime":"","EndTime":"","Snippet":"","PopupInfo":"","HasLabel":-1,"LabelID":0}},
{"type":"Feature","geometry":{"type":"Point","coordinates":[6.340540000000033,50.828595000000064,0,-1.7976931348623157e+308]},"properties":{"Name":"104th ID","FolderPath":"1944-12-27T00:00:01Z","SymbolID":5,"AltMode":-1,"Base":0,"TimeSpan":0,"TimeStamp":0,"BeginTime":"","EndTime":"","Snippet":"","PopupInfo":"","HasLabel":-1,"LabelID":0}},
{"type":"Feature","geometry":{"type":"Point","coordinates":[5.939389000000062,50.63471300000003,0,-1.7976931348623157e+308]},"properties":{"Name":"5th AD","FolderPath":"1944-12-27T00:00:01Z","SymbolID":5,"AltMode":-1,"Base":0,"TimeSpan":0,"TimeStamp":0,"BeginTime":"","EndTime":"","Snippet":"","PopupInfo":"","HasLabel":-1,"LabelID":0}},
{"type":"Feature","geometry":{"type":"Point","coordinates":[6.205539000000044,50.639320000000055,0,-1.7976931348623157e+308]},"properties":{"Name":"78th ID","FolderPath":"1944-12-27T00:00:01Z","SymbolID":5,"AltMode":-1,"Base":0,"TimeSpan":0,"TimeStamp":0,"BeginTime":"","EndTime":"","Snippet":"","PopupInfo":"","HasLabel":-1,"LabelID":0}},
{"type":"Feature","geometry":{"type":"Point","coordinates":[6.313267000000053,50.69441000000006,0,-1.7976931348623157e+308]},"properties":{"Name":"8th ID","FolderPath":"1944-12-27T00:00:01Z","SymbolID":5,"AltMode":-1,"Base":0,"TimeSpan":0,"TimeStamp":0,"BeginTime":"","EndTime":"","Snippet":"","PopupInfo":"","HasLabel":-1,"LabelID":0}},
{"type":"Feature","geometry":{"type":"Point","coordinates":[5.567162000000053,50.57797700000003,0,-1.7976931348623157e+308]},"properties":{"Name":"51st ID","FolderPath":"1944-12-27T00:00:01Z","SymbolID":0,"AltMode":-1,"Base":0,"TimeSpan":0,"TimeStamp":0,"BeginTime":"","EndTime":"","Snippet":"","PopupInfo":"","HasLabel":-1,"LabelID":0}},
{"type":"Feature","geometry":{"type":"Point","coordinates":[5.951381000000026,50.443035000000066,0,-1.7976931348623157e+308]},"properties":{"Name":"30th ID","FolderPath":"1944-12-27T00:00:01Z","SymbolID":5,"AltMode":-1,"Base":0,"TimeSpan":0,"TimeStamp":0,"BeginTime":"","EndTime":"","Snippet":"","PopupInfo":"","HasLabel":-1,"LabelID":0}},
{"type":"Feature","geometry":{"type":"Point","coordinates":[6.055266000000074,50.48705200000006,0,-1.7976931348623157e+308]},"properties":{"Name":"1st ID","FolderPath":"1944-12-27T00:00:01Z","SymbolID":5,"AltMode":-1,"Base":0,"TimeSpan":0,"TimeStamp":0,"BeginTime":"","EndTime":"","Snippet":"","PopupInfo":"","HasLabel":-1,"LabelID":0}},
{"type":"Feature","geometry":{"type":"Point","coordinates":[6.152955000000077,50.45408100000003,0,-1.7976931348623157e+308]},"properties":{"Name":"2nd ID","FolderPath":"1944-12-27T00:00:01Z","SymbolID":5,"AltMode":-1,"Base":0,"TimeSpan":0,"TimeStamp":0,"BeginTime":"","EndTime":"","Snippet":"","PopupInfo":"","HasLabel":-1,"LabelID":0}},
{"type":"Feature","geometry":{"type":"Point","coordinates":[6.154710000000023,50.49080600000008,0,-1.7976931348623157e+308]},"properties":{"Name":"99th ID","FolderPath":"1944-12-27T00:00:01Z","SymbolID":5,"AltMode":-1,"Base":0,"TimeSpan":0,"TimeStamp":0,"BeginTime":"","EndTime":"","Snippet":"","PopupInfo":"","HasLabel":-1,"LabelID":0}},
{"type":"Feature","geometry":{"type":"Point","coordinates":[6.124291000000028,50.53619700000007,0,-1.7976931348623157e+308]},"properties":{"Name":"9th ID","FolderPath":"1944-12-27T00:00:01Z","SymbolID":5,"AltMode":-1,"Base":0,"TimeSpan":0,"TimeStamp":0,"BeginTime":"","EndTime":"","Snippet":"","PopupInfo":"","HasLabel":-1,"LabelID":0}},
{"type":"Feature","geometry":{"type":"Point","coordinates":[5.375450000000058,50.47046400000005,0,-1.7976931348623157e+308]},"properties":{"Name":"83rd ID","FolderPath":"1944-12-27T00:00:01Z","SymbolID":5,"AltMode":-1,"Base":0,"TimeSpan":0,"TimeStamp":0,"BeginTime":"","EndTime":"","Snippet":"","PopupInfo":"","HasLabel":-1,"LabelID":0}},
{"type":"Feature","geometry":{"type":"Point","coordinates":[5.368013000000076,50.298711000000026,0,-1.7976931348623157e+308]},"properties":{"Name":"84th ID","FolderPath":"1944-12-27T00:00:01Z","SymbolID":5,"AltMode":-1,"Base":0,"TimeSpan":0,"TimeStamp":0,"BeginTime":"","EndTime":"","Snippet":"","PopupInfo":"","HasLabel":-1,"LabelID":0}},
{"type":"Feature","geometry":{"type":"Point","coordinates":[5.507747000000052,50.30222700000007,0,-1.7976931348623157e+308]},"properties":{"Name":"75th ID","FolderPath":"1944-12-27T00:00:01Z","SymbolID":5,"AltMode":-1,"Base":0,"TimeSpan":0,"TimeStamp":0,"BeginTime":"","EndTime":"","Snippet":"","PopupInfo":"","HasLabel":-1,"LabelID":0}},
{"type":"Feature","geometry":{"type":"Point","coordinates":[5.622153000000026,50.43005800000003,0,-1.7976931348623157e+308]},"properties":{"Name":"106th ID","FolderPath":"1944-12-27T00:00:01Z","SymbolID":5,"AltMode":-1,"Base":0,"TimeSpan":0,"TimeStamp":0,"BeginTime":"","EndTime":"","Snippet":"","PopupInfo":"","HasLabel":-1,"LabelID":0}},
{"type":"Feature","geometry":{"type":"Point","coordinates":[5.568073000000027,50.30214200000006,0,-1.7976931348623157e+308]},"properties":{"Name":"3rd AD","FolderPath":"1944-12-27T00:00:01Z","SymbolID":5,"AltMode":-1,"Base":0,"TimeSpan":0,"TimeStamp":0,"BeginTime":"","EndTime":"","Snippet":"","PopupInfo":"","HasLabel":-1,"LabelID":0}},
{"type":"Feature","geometry":{"type":"Point","coordinates":[5.702301000000034,50.33886000000007,0,-1.7976931348623157e+308]},"properties":{"Name":"7th AD","FolderPath":"1944-12-27T00:00:01Z","SymbolID":5,"AltMode":-1,"Base":0,"TimeSpan":0,"TimeStamp":0,"BeginTime":"","EndTime":"","Snippet":"","PopupInfo":"","HasLabel":-1,"LabelID":0}},
{"type":"Feature","geometry":{"type":"Point","coordinates":[5.782916000000057,50.372944000000075,0,-1.7976931348623157e+308]},"properties":{"Name":"82nd AB","FolderPath":"1944-12-27T00:00:01Z","SymbolID":6,"AltMode":-1,"Base":0,"TimeSpan":0,"TimeStamp":0,"BeginTime":"","EndTime":"","Snippet":"","PopupInfo":"","HasLabel":-1,"LabelID":0}},
{"type":"Feature","geometry":{"type":"Point","coordinates":[5.0822540000000345,50.25831100000005,0,-1.7976931348623157e+308]},"properties":{"Name":"2nd AD","FolderPath":"1944-12-27T00:00:01Z","SymbolID":7,"AltMode":-1,"Base":0,"TimeSpan":0,"TimeStamp":0,"BeginTime":"","EndTime":"","Snippet":"","PopupInfo":"","HasLabel":-1,"LabelID":0}},
{"type":"Feature","geometry":{"type":"Point","coordinates":[4.69940900000006,50.22050900000005,0,-1.7976931348623157e+308]},"properties":{"Name":"6th AD","FolderPath":"1944-12-27T00:00:01Z","SymbolID":7,"AltMode":-1,"Base":0,"TimeSpan":0,"TimeStamp":0,"BeginTime":"","EndTime":"","Snippet":"","PopupInfo":"","HasLabel":-1,"LabelID":0}},
{"type":"Feature","geometry":{"type":"Point","coordinates":[5.247010000000046,49.90347600000007,0,-1.7976931348623157e+308]},"properties":{"Name":"9th AD","FolderPath":"1944-12-27T00:00:01Z","SymbolID":7,"AltMode":-1,"Base":0,"TimeSpan":0,"TimeStamp":0,"BeginTime":"","EndTime":"","Snippet":"","PopupInfo":"","HasLabel":-1,"LabelID":0}},
{"type":"Feature","geometry":{"type":"Point","coordinates":[5.481104000000073,49.825844000000075,0,-1.7976931348623157e+308]},"properties":{"Name":"28th ID","FolderPath":"1944-12-27T00:00:01Z","SymbolID":5,"AltMode":-1,"Base":0,"TimeSpan":0,"TimeStamp":0,"BeginTime":"","EndTime":"","Snippet":"","PopupInfo":"","HasLabel":-1,"LabelID":0}},
{"type":"Feature","geometry":{"type":"Point","coordinates":[5.68494400000003,50.027922000000046,0,-1.7976931348623157e+308]},"properties":{"Name":"101st AB","FolderPath":"1944-12-27T00:00:01Z","SymbolID":8,"AltMode":-1,"Base":0,"TimeSpan":0,"TimeStamp":0,"BeginTime":"","EndTime":"","Snippet":"","PopupInfo":"","HasLabel":-1,"LabelID":0}},
{"type":"Feature","geometry":{"type":"Point","coordinates":[5.687212000000045,49.85307300000005,0,-1.7976931348623157e+308]},"properties":{"Name":"4th AD","FolderPath":"1944-12-27T00:00:01Z","SymbolID":7,"AltMode":-1,"Base":0,"TimeSpan":0,"TimeStamp":0,"BeginTime":"","EndTime":"","Snippet":"","PopupInfo":"","HasLabel":-1,"LabelID":0}},
{"type":"Feature","geometry":{"type":"Point","coordinates":[5.78119700000002,49.786118000000045,0,-1.7976931348623157e+308]},"properties":{"Name":"35th ID","FolderPath":"1944-12-27T00:00:01Z","SymbolID":5,"AltMode":-1,"Base":0,"TimeSpan":0,"TimeStamp":0,"BeginTime":"","EndTime":"","Snippet":"","PopupInfo":"","HasLabel":-1,"LabelID":0}},
{"type":"Feature","geometry":{"type":"Point","coordinates":[5.907452000000035,49.82262900000006,0,-1.7976931348623157e+308]},"properties":{"Name":"26th ID","FolderPath":"1944-12-27T00:00:01Z","SymbolID":5,"AltMode":-1,"Base":0,"TimeSpan":0,"TimeStamp":0,"BeginTime":"","EndTime":"","Snippet":"","PopupInfo":"","HasLabel":-1,"LabelID":0}},
{"type":"Feature","geometry":{"type":"Point","coordinates":[6.049477000000024,49.811078000000066,0,-1.7976931348623157e+308]},"properties":{"Name":"80th ID","FolderPath":"1944-12-27T00:00:01Z","SymbolID":5,"AltMode":-1,"Base":0,"TimeSpan":0,"TimeStamp":0,"BeginTime":"","EndTime":"","Snippet":"","PopupInfo":"","HasLabel":-1,"LabelID":0}},
{"type":"Feature","geometry":{"type":"Point","coordinates":[6.274350000000027,49.72576000000004,0,-1.7976931348623157e+308]},"properties":{"Name":"10th AD","FolderPath":"1944-12-27T00:00:01Z","SymbolID":7,"AltMode":-1,"Base":0,"TimeSpan":0,"TimeStamp":0,"BeginTime":"","EndTime":"","Snippet":"","PopupInfo":"","HasLabel":-1,"LabelID":0}},
{"type":"Feature","geometry":{"type":"Point","coordinates":[6.375730000000033,49.75940700000007,0,-1.7976931348623157e+308]},"properties":{"Name":"5th ID","FolderPath":"1944-12-27T00:00:01Z","SymbolID":5,"AltMode":-1,"Base":0,"TimeSpan":0,"TimeStamp":0,"BeginTime":"","EndTime":"","Snippet":"","PopupInfo":"","HasLabel":-1,"LabelID":0}},
{"type":"Feature","geometry":{"type":"Point","coordinates":[6.296685000000025,49.607972000000075,0,-1.7976931348623157e+308]},"properties":{"Name":"4th ID","FolderPath":"1944-12-27T00:00:01Z","SymbolID":5,"AltMode":-1,"Base":0,"TimeSpan":0,"TimeStamp":0,"BeginTime":"","EndTime":"","Snippet":"","PopupInfo":"","HasLabel":-1,"LabelID":0}},
{"type":"Feature","geometry":{"type":"Point","coordinates":[4.487640000000056,49.62180500000005,0,-1.7976931348623157e+308]},"properties":{"Name":"11th AD","FolderPath":"1944-12-27T00:00:01Z","SymbolID":7,"AltMode":-1,"Base":0,"TimeSpan":0,"TimeStamp":0,"BeginTime":"","EndTime":"","Snippet":"","PopupInfo":"","HasLabel":-1,"LabelID":0}},
{"type":"Feature","geometry":{"type":"Point","coordinates":[6.544574000000068,49.37984300000005,0,-1.7976931348623157e+308]},"properties":{"Name":"90th ID","FolderPath":"1944-12-27T00:00:01Z","SymbolID":5,"AltMode":-1,"Base":0,"TimeSpan":0,"TimeStamp":0,"BeginTime":"","EndTime":"","Snippet":"","PopupInfo":"","HasLabel":-1,"LabelID":0}},
{"type":"Feature","geometry":{"type":"Point","coordinates":[6.6721070000000395,49.28905300000008,0,-1.7976931348623157e+308]},"properties":{"Name":"95th ID","FolderPath":"1944-12-27T00:00:01Z","SymbolID":5,"AltMode":-1,"Base":0,"TimeSpan":0,"TimeStamp":0,"BeginTime":"","EndTime":"","Snippet":"","PopupInfo":"","HasLabel":-1,"LabelID":0}},
{"type":"Feature","geometry":{"type":"Point","coordinates":[6.807329000000038,49.12823300000008,0,-1.7976931348623157e+308]},"properties":{"Name":"103rd ID","FolderPath":"1944-12-27T00:00:01Z","SymbolID":5,"AltMode":-1,"Base":0,"TimeSpan":0,"TimeStamp":0,"BeginTime":"","EndTime":"","Snippet":"","PopupInfo":"","HasLabel":-1,"LabelID":0}},
{"type":"Feature","geometry":{"type":"Point","coordinates":[7.0864160000000425,49.05683200000004,0,-1.7976931348623157e+308]},"properties":{"Name":"44th ID","FolderPath":"1944-12-27T00:00:01Z","SymbolID":5,"AltMode":-1,"Base":0,"TimeSpan":0,"TimeStamp":0,"BeginTime":"","EndTime":"","Snippet":"","PopupInfo":"","HasLabel":-1,"LabelID":0}},
{"type":"Feature","geometry":{"type":"Point","coordinates":[7.281897000000072,49.035142000000064,0,-1.7976931348623157e+308]},"properties":{"Name":"100th ID","FolderPath":"1944-12-27T00:00:01Z","SymbolID":5,"AltMode":-1,"Base":0,"TimeSpan":0,"TimeStamp":0,"BeginTime":"","EndTime":"","Snippet":"","PopupInfo":"","HasLabel":-1,"LabelID":0}},
{"type":"Feature","geometry":{"type":"Point","coordinates":[6.235059000000035,49.08389500000004,0,-1.7976931348623157e+308]},"properties":{"Name":"6th AD","FolderPath":"1944-12-27T00:00:01Z","SymbolID":7,"AltMode":-1,"Base":0,"TimeSpan":0,"TimeStamp":0,"BeginTime":"","EndTime":"","Snippet":"","PopupInfo":"","HasLabel":-1,"LabelID":0}},
{"type":"Feature","geometry":{"type":"Point","coordinates":[6.701426000000026,48.81100200000003,0,-1.7976931348623157e+308]},"properties":{"Name":"87th ID","FolderPath":"1944-12-27T00:00:01Z","SymbolID":5,"AltMode":-1,"Base":0,"TimeSpan":0,"TimeStamp":0,"BeginTime":"","EndTime":"","Snippet":"","PopupInfo":"","HasLabel":-1,"LabelID":0}},
{"type":"Feature","geometry":{"type":"Point","coordinates":[7.093108000000029,48.830876000000046,0,-1.7976931348623157e+308]},"properties":{"Name":"12th AD","FolderPath":"1944-12-27T00:00:01Z","SymbolID":7,"AltMode":-1,"Base":0,"TimeSpan":0,"TimeStamp":0,"BeginTime":"","EndTime":"","Snippet":"","PopupInfo":"","HasLabel":-1,"LabelID":0}},
{"type":"Feature","geometry":{"type":"Point","coordinates":[7.90341200000006,48.90497700000003,0,-1.7976931348623157e+308]},"properties":{"Name":"14th AD","FolderPath":"1944-12-27T00:00:01Z","SymbolID":7,"AltMode":-1,"Base":0,"TimeSpan":0,"TimeStamp":0,"BeginTime":"","EndTime":"","Snippet":"","PopupInfo":"","HasLabel":-1,"LabelID":0}},
{"type":"Feature","geometry":{"type":"Point","coordinates":[7.8178080000000705,49.02148200000005,0,-1.7976931348623157e+308]},"properties":{"Name":"45th ID","FolderPath":"1944-12-27T00:00:01Z","SymbolID":5,"AltMode":-1,"Base":0,"TimeSpan":0,"TimeStamp":0,"BeginTime":"","EndTime":"","Snippet":"","PopupInfo":"","HasLabel":-1,"LabelID":0}},
{"type":"Feature","geometry":{"type":"Point","coordinates":[8.091478000000052,48.97441800000007,0,-1.7976931348623157e+308]},"properties":{"Name":"79th ID","FolderPath":"1944-12-27T00:00:01Z","SymbolID":5,"AltMode":-1,"Base":0,"TimeSpan":0,"TimeStamp":0,"BeginTime":"","EndTime":"","Snippet":"","PopupInfo":"","HasLabel":-1,"LabelID":0}},
{"type":"Feature","geometry":{"type":"Point","coordinates":[7.935057000000029,48.82798600000007,0,-1.7976931348623157e+308]},"properties":{"Name":"63rd ID","FolderPath":"1944-12-27T00:00:01Z","SymbolID":5,"AltMode":-1,"Base":0,"TimeSpan":0,"TimeStamp":0,"BeginTime":"","EndTime":"","Snippet":"","PopupInfo":"","HasLabel":-1,"LabelID":0}},
{"type":"Feature","geometry":{"type":"Point","coordinates":[7.519025000000056,48.59984900000006,0,-1.7976931348623157e+308]},"properties":{"Name":"36th ID","FolderPath":"1944-12-27T00:00:01Z","SymbolID":5,"AltMode":-1,"Base":0,"TimeSpan":0,"TimeStamp":0,"BeginTime":"","EndTime":"","Snippet":"","PopupInfo":"","HasLabel":-1,"LabelID":0}},
{"type":"Feature","geometry":{"type":"Point","coordinates":[7.638522000000023,48.55644100000006,0,-1.7976931348623157e+308]},"properties":{"Name":"42nd ID","FolderPath":"1944-12-27T00:00:01Z","SymbolID":5,"AltMode":-1,"Base":0,"TimeSpan":0,"TimeStamp":0,"BeginTime":"","EndTime":"","Snippet":"","PopupInfo":"","HasLabel":-1,"LabelID":0}},
{"type":"Feature","geometry":{"type":"Point","coordinates":[7.5390200000000505,48.33037000000007,0,-1.7976931348623157e+308]},"properties":{"Name":"2nd AD (FR)","FolderPath":"1944-12-27T00:00:01Z","SymbolID":9,"AltMode":-1,"Base":0,"TimeSpan":0,"TimeStamp":0,"BeginTime":"","EndTime":"","Snippet":"","PopupInfo":"","HasLabel":-1,"LabelID":0}},
{"type":"Feature","geometry":{"type":"Point","coordinates":[7.285449000000028,48.151185000000055,0,-1.7976931348623157e+308]},"properties":{"Name":"3rd ID","FolderPath":"1944-12-27T00:00:01Z","SymbolID":5,"AltMode":-1,"Base":0,"TimeSpan":0,"TimeStamp":0,"BeginTime":"","EndTime":"","Snippet":"","PopupInfo":"","HasLabel":-1,"LabelID":0}},
{"type":"Feature","geometry":{"type":"Point","coordinates":[6.943572000000074,48.08000700000008,0,-1.7976931348623157e+308]},"properties":{"Name":"3rd ID (ALG)","FolderPath":"1944-12-27T00:00:01Z","SymbolID":10,"AltMode":-1,"Base":0,"TimeSpan":0,"TimeStamp":0,"BeginTime":"","EndTime":"","Snippet":"","PopupInfo":"","HasLabel":-1,"LabelID":0}},
{"type":"Feature","geometry":{"type":"Point","coordinates":[6.573694000000046,50.27760500000005,0,-1.7976931348623157e+308]},"properties":{"Name":"10th SS AD (?)","FolderPath":"1944-12-27T00:00:01Z","SymbolID":11,"AltMode":-1,"Base":0,"TimeSpan":0,"TimeStamp":0,"BeginTime":"","EndTime":"","Snippet":"","PopupInfo":"","HasLabel":-1,"LabelID":0}},
{"type":"Feature","geometry":{"type":"Point","coordinates":[4.377473000000066,51.737595000000056,0,-1.7976931348623157e+308]},"properties":{"Name":"346th ID","FolderPath":"1944-12-27T00:00:01Z","SymbolID":12,"AltMode":-1,"Base":0,"TimeSpan":0,"TimeStamp":0,"BeginTime":"","EndTime":"","Snippet":"","PopupInfo":"","HasLabel":-1,"LabelID":0}},
{"type":"Feature","geometry":{"type":"Point","coordinates":[4.915665000000047,51.777063000000055,0,-1.7976931348623157e+308]},"properties":{"Name":"711th ID","FolderPath":"1944-12-27T00:00:01Z","SymbolID":12,"AltMode":-1,"Base":0,"TimeSpan":0,"TimeStamp":0,"BeginTime":"","EndTime":"","Snippet":"","PopupInfo":"","HasLabel":-1,"LabelID":0}},
{"type":"Feature","geometry":{"type":"Point","coordinates":[5.159042000000056,51.84669700000006,0,-1.7976931348623157e+308]},"properties":{"Name":"6th AirD","FolderPath":"1944-12-27T00:00:01Z","SymbolID":13,"AltMode":-1,"Base":0,"TimeSpan":0,"TimeStamp":0,"BeginTime":"","EndTime":"","Snippet":"","PopupInfo":"","HasLabel":-1,"LabelID":0}},
{"type":"Feature","geometry":{"type":"Point","coordinates":[5.366153000000054,51.920870000000036,0,-1.7976931348623157e+308]},"properties":{"Name":"712th ID","FolderPath":"1944-12-27T00:00:01Z","SymbolID":12,"AltMode":-1,"Base":0,"TimeSpan":0,"TimeStamp":0,"BeginTime":"","EndTime":"","Snippet":"","PopupInfo":"","HasLabel":-1,"LabelID":0}},
{"type":"Feature","geometry":{"type":"Point","coordinates":[5.889844000000039,51.96692600000006,0,-1.7976931348623157e+308]},"properties":{"Name":"2nd AirD","FolderPath":"1944-12-27T00:00:01Z","SymbolID":13,"AltMode":-1,"Base":0,"TimeSpan":0,"TimeStamp":0,"BeginTime":"","EndTime":"","Snippet":"","PopupInfo":"","HasLabel":-1,"LabelID":0}},
{"type":"Feature","geometry":{"type":"Point","coordinates":[6.108606000000066,51.74954900000006,0,-1.7976931348623157e+308]},"properties":{"Name":"84th ID","FolderPath":"1944-12-27T00:00:01Z","SymbolID":12,"AltMode":-1,"Base":0,"TimeSpan":0,"TimeStamp":0,"BeginTime":"","EndTime":"","Snippet":"","PopupInfo":"","HasLabel":-1,"LabelID":0}},
{"type":"Feature","geometry":{"type":"Point","coordinates":[6.534048000000041,51.81257100000005,0,-1.7976931348623157e+308]},"properties":{"Name":"8th AirD","FolderPath":"1944-12-27T00:00:01Z","SymbolID":13,"AltMode":-1,"Base":0,"TimeSpan":0,"TimeStamp":0,"BeginTime":"","EndTime":"","Snippet":"","PopupInfo":"","HasLabel":-1,"LabelID":0}},
{"type":"Feature","geometry":{"type":"Point","coordinates":[6.088350000000048,51.65150600000004,0,-1.7976931348623157e+308]},"properties":{"Name":"50th ID","FolderPath":"1944-12-27T00:00:01Z","SymbolID":12,"AltMode":-1,"Base":0,"TimeSpan":0,"TimeStamp":0,"BeginTime":"","EndTime":"","Snippet":"","PopupInfo":"","HasLabel":-1,"LabelID":0}},
{"type":"Feature","geometry":{"type":"Point","coordinates":[6.2014160000000516,51.590787000000034,0,-1.7976931348623157e+308]},"properties":{"Name":"406th ID","FolderPath":"1944-12-27T00:00:01Z","SymbolID":12,"AltMode":-1,"Base":0,"TimeSpan":0,"TimeStamp":0,"BeginTime":"","EndTime":"","Snippet":"","PopupInfo":"","HasLabel":-1,"LabelID":0}},
{"type":"Feature","geometry":{"type":"Point","coordinates":[6.205932000000075,51.328832000000034,0,-1.7976931348623157e+308]},"properties":{"Name":"7th AirD","FolderPath":"1944-12-27T00:00:01Z","SymbolID":13,"AltMode":-1,"Base":0,"TimeSpan":0,"TimeStamp":0,"BeginTime":"","EndTime":"","Snippet":"","PopupInfo":"","HasLabel":-1,"LabelID":0}},
{"type":"Feature","geometry":{"type":"Point","coordinates":[6.570746000000042,51.23800200000005,0,-1.7976931348623157e+308]},"properties":{"Name":"59th ID","FolderPath":"1944-12-27T00:00:01Z","SymbolID":12,"AltMode":-1,"Base":0,"TimeSpan":0,"TimeStamp":0,"BeginTime":"","EndTime":"","Snippet":"","PopupInfo":"","HasLabel":-1,"LabelID":0}},
{"type":"Feature","geometry":{"type":"Point","coordinates":[6.287191000000064,51.428931000000034,0,-1.7976931348623157e+308]},"properties":{"Name":"180th ID","FolderPath":"1944-12-27T00:00:01Z","SymbolID":12,"AltMode":-1,"Base":0,"TimeSpan":0,"TimeStamp":0,"BeginTime":"","EndTime":"","Snippet":"","PopupInfo":"","HasLabel":-1,"LabelID":0}},
{"type":"Feature","geometry":{"type":"Point","coordinates":[6.071526000000063,51.211231000000055,0,-1.7976931348623157e+308]},"properties":{"Name":"606th ZBV ID","FolderPath":"1944-12-27T00:00:01Z","SymbolID":12,"AltMode":-1,"Base":0,"TimeSpan":0,"TimeStamp":0,"BeginTime":"","EndTime":"","Snippet":"","PopupInfo":"","HasLabel":-1,"LabelID":0}},
{"type":"Feature","geometry":{"type":"Point","coordinates":[6.0357680000000755,51.04693400000008,0,-1.7976931348623157e+308]},"properties":{"Name":"176th ID","FolderPath":"1944-12-27T00:00:01Z","SymbolID":12,"AltMode":-1,"Base":0,"TimeSpan":0,"TimeStamp":0,"BeginTime":"","EndTime":"","Snippet":"","PopupInfo":"","HasLabel":-1,"LabelID":0}},
{"type":"Feature","geometry":{"type":"Point","coordinates":[6.1879390000000285,51.022511000000065,0,-1.7976931348623157e+308]},"properties":{"Name":"183rd ID","FolderPath":"1944-12-27T00:00:01Z","SymbolID":12,"AltMode":-1,"Base":0,"TimeSpan":0,"TimeStamp":0,"BeginTime":"","EndTime":"","Snippet":"","PopupInfo":"","HasLabel":-1,"LabelID":0}},
{"type":"Feature","geometry":{"type":"Point","coordinates":[6.3662610000000655,50.97806000000003,0,-1.7976931348623157e+308]},"properties":{"Name":"340th ID","FolderPath":"1944-12-27T00:00:01Z","SymbolID":12,"AltMode":-1,"Base":0,"TimeSpan":0,"TimeStamp":0,"BeginTime":"","EndTime":"","Snippet":"","PopupInfo":"","HasLabel":-1,"LabelID":0}},
{"type":"Feature","geometry":{"type":"Point","coordinates":[6.482726000000071,50.89703300000008,0,-1.7976931348623157e+308]},"properties":{"Name":"363rd ID","FolderPath":"1944-12-27T00:00:01Z","SymbolID":12,"AltMode":-1,"Base":0,"TimeSpan":0,"TimeStamp":0,"BeginTime":"","EndTime":"","Snippet":"","PopupInfo":"","HasLabel":-1,"LabelID":0}},
{"type":"Feature","geometry":{"type":"Point","coordinates":[6.543791000000056,50.83048700000006,0,-1.7976931348623157e+308]},"properties":{"Name":"47th ID","FolderPath":"1944-12-27T00:00:01Z","SymbolID":12,"AltMode":-1,"Base":0,"TimeSpan":0,"TimeStamp":0,"BeginTime":"","EndTime":"","Snippet":"","PopupInfo":"","HasLabel":-1,"LabelID":0}},
{"type":"Feature","geometry":{"type":"Point","coordinates":[6.525454000000025,50.678900000000056,0,-1.7976931348623157e+308]},"properties":{"Name":"246th ID","FolderPath":"1944-12-27T00:00:01Z","SymbolID":12,"AltMode":-1,"Base":0,"TimeSpan":0,"TimeStamp":0,"BeginTime":"","EndTime":"","Snippet":"","PopupInfo":"","HasLabel":-1,"LabelID":0}},
{"type":"Feature","geometry":{"type":"Point","coordinates":[6.54069400000003,50.726698000000056,0,-1.7976931348623157e+308]},"properties":{"Name":"353rd ID","FolderPath":"1944-12-27T00:00:01Z","SymbolID":12,"AltMode":-1,"Base":0,"TimeSpan":0,"TimeStamp":0,"BeginTime":"","EndTime":"","Snippet":"","PopupInfo":"","HasLabel":-1,"LabelID":0}},
{"type":"Feature","geometry":{"type":"Point","coordinates":[6.68625000000003,50.68016800000004,0,-1.7976931348623157e+308]},"properties":{"Name":"89th ID","FolderPath":"1944-12-27T00:00:01Z","SymbolID":12,"AltMode":-1,"Base":0,"TimeSpan":0,"TimeStamp":0,"BeginTime":"","EndTime":"","Snippet":"","PopupInfo":"","HasLabel":-1,"LabelID":0}},
{"type":"Feature","geometry":{"type":"Point","coordinates":[6.728527000000042,50.642554000000075,0,-1.7976931348623157e+308]},"properties":{"Name":"272nd ID","FolderPath":"1944-12-27T00:00:01Z","SymbolID":12,"AltMode":-1,"Base":0,"TimeSpan":0,"TimeStamp":0,"BeginTime":"","EndTime":"","Snippet":"","PopupInfo":"","HasLabel":-1,"LabelID":0}},
{"type":"Feature","geometry":{"type":"Point","coordinates":[6.470882000000074,50.634907000000055,0,-1.7976931348623157e+308]},"properties":{"Name":"85th ID","FolderPath":"1944-12-27T00:00:01Z","SymbolID":12,"AltMode":-1,"Base":0,"TimeSpan":0,"TimeStamp":0,"BeginTime":"","EndTime":"","Snippet":"","PopupInfo":"","HasLabel":-1,"LabelID":0}},
{"type":"Feature","geometry":{"type":"Point","coordinates":[6.371988000000044,50.58422500000006,0,-1.7976931348623157e+308]},"properties":{"Name":"32nd ID","FolderPath":"1944-12-27T00:00:01Z","SymbolID":12,"AltMode":-1,"Base":0,"TimeSpan":0,"TimeStamp":0,"BeginTime":"","EndTime":"","Snippet":"","PopupInfo":"","HasLabel":-1,"LabelID":0}},
{"type":"Feature","geometry":{"type":"Point","coordinates":[6.380532000000073,50.533795000000055,0,-1.7976931348623157e+308]},"properties":{"Name":"3rd AD","FolderPath":"1944-12-27T00:00:01Z","SymbolID":11,"AltMode":-1,"Base":0,"TimeSpan":0,"TimeStamp":0,"BeginTime":"","EndTime":"","Snippet":"","PopupInfo":"","HasLabel":-1,"LabelID":0}},
{"type":"Feature","geometry":{"type":"Point","coordinates":[6.319683000000055,50.45124400000003,0,-1.7976931348623157e+308]},"properties":{"Name":"277th ID","FolderPath":"1944-12-27T00:00:01Z","SymbolID":12,"AltMode":-1,"Base":0,"TimeSpan":0,"TimeStamp":0,"BeginTime":"","EndTime":"","Snippet":"","PopupInfo":"","HasLabel":-1,"LabelID":0}},
{"type":"Feature","geometry":{"type":"Point","coordinates":[6.344435000000033,50.405328000000054,0,-1.7976931348623157e+308]},"properties":{"Name":"12th ID","FolderPath":"1944-12-27T00:00:01Z","SymbolID":12,"AltMode":-1,"Base":0,"TimeSpan":0,"TimeStamp":0,"BeginTime":"","EndTime":"","Snippet":"","PopupInfo":"","HasLabel":-1,"LabelID":0}},
{"type":"Feature","geometry":{"type":"Point","coordinates":[6.217992000000038,50.381042000000036,0,-1.7976931348623157e+308]},"properties":{"Name":"12th SS AD","FolderPath":"1944-12-27T00:00:01Z","SymbolID":11,"AltMode":-1,"Base":0,"TimeSpan":0,"TimeStamp":0,"BeginTime":"","EndTime":"","Snippet":"","PopupInfo":"","HasLabel":-1,"LabelID":0}},
{"type":"Feature","geometry":{"type":"Point","coordinates":[6.12596300000007,50.33206400000006,0,-1.7976931348623157e+308]},"properties":{"Name":"18th ID","FolderPath":"1944-12-27T00:00:01Z","SymbolID":12,"AltMode":-1,"Base":0,"TimeSpan":0,"TimeStamp":0,"BeginTime":"","EndTime":"","Snippet":"","PopupInfo":"","HasLabel":-1,"LabelID":0}},
{"type":"Feature","geometry":{"type":"Point","coordinates":[6.108028000000047,50.386802000000046,0,-1.7976931348623157e+308]},"properties":{"Name":"3rd AirD","FolderPath":"1944-12-27T00:00:01Z","SymbolID":13,"AltMode":-1,"Base":0,"TimeSpan":0,"TimeStamp":0,"BeginTime":"","EndTime":"","Snippet":"","PopupInfo":"","HasLabel":-1,"LabelID":0}},
{"type":"Feature","geometry":{"type":"Point","coordinates":[5.987419000000045,50.35322700000006,0,-1.7976931348623157e+308]},"properties":{"Name":"1st SS AD","FolderPath":"1944-12-27T00:00:01Z","SymbolID":11,"AltMode":-1,"Base":0,"TimeSpan":0,"TimeStamp":0,"BeginTime":"","EndTime":"","Snippet":"","PopupInfo":"","HasLabel":-1,"LabelID":0}},
{"type":"Feature","geometry":{"type":"Point","coordinates":[5.895910000000072,50.32078800000005,0,-1.7976931348623157e+308]},"properties":{"Name":"9th SS AD","FolderPath":"1944-12-27T00:00:01Z","SymbolID":11,"AltMode":-1,"Base":0,"TimeSpan":0,"TimeStamp":0,"BeginTime":"","EndTime":"","Snippet":"","PopupInfo":"","HasLabel":-1,"LabelID":0}},
{"type":"Feature","geometry":{"type":"Point","coordinates":[5.811070000000029,50.28901100000007,0,-1.7976931348623157e+308]},"properties":{"Name":"62nd ID","FolderPath":"1944-12-27T00:00:01Z","SymbolID":12,"AltMode":-1,"Base":0,"TimeSpan":0,"TimeStamp":0,"BeginTime":"","EndTime":"","Snippet":"","PopupInfo":"","HasLabel":-1,"LabelID":0}},
{"type":"Feature","geometry":{"type":"Point","coordinates":[5.718267000000026,50.233276000000046,0,-1.7976931348623157e+308]},"properties":{"Name":"2nd SS AD","FolderPath":"1944-12-27T00:00:01Z","SymbolID":11,"AltMode":-1,"Base":0,"TimeSpan":0,"TimeStamp":0,"BeginTime":"","EndTime":"","Snippet":"","PopupInfo":"","HasLabel":-1,"LabelID":0}},
{"type":"Feature","geometry":{"type":"Point","coordinates":[5.6015650000000505,50.215809000000036,0,-1.7976931348623157e+308]},"properties":{"Name":"GD AD (2)","FolderPath":"1944-12-27T00:00:01Z","SymbolID":11,"AltMode":-1,"Base":0,"TimeSpan":0,"TimeStamp":0,"BeginTime":"","EndTime":"","Snippet":"","PopupInfo":"","HasLabel":-1,"LabelID":0}},
{"type":"Feature","geometry":{"type":"Point","coordinates":[5.482531000000051,50.238230000000044,0,-1.7976931348623157e+308]},"properties":{"Name":"560th ID","FolderPath":"1944-12-27T00:00:01Z","SymbolID":12,"AltMode":-1,"Base":0,"TimeSpan":0,"TimeStamp":0,"BeginTime":"","EndTime":"","Snippet":"","PopupInfo":"","HasLabel":-1,"LabelID":0}},
{"type":"Feature","geometry":{"type":"Point","coordinates":[5.548537000000067,50.16114700000003,0,-1.7976931348623157e+308]},"properties":{"Name":"11th AD","FolderPath":"1944-12-27T00:00:01Z","SymbolID":11,"AltMode":-1,"Base":0,"TimeSpan":0,"TimeStamp":0,"BeginTime":"","EndTime":"","Snippet":"","PopupInfo":"","HasLabel":-1,"LabelID":0}},
{"type":"Feature","geometry":{"type":"Point","coordinates":[5.44105600000006,50.17812900000007,0,-1.7976931348623157e+308]},"properties":{"Name":"116th AD","FolderPath":"1944-12-27T00:00:01Z","SymbolID":11,"AltMode":-1,"Base":0,"TimeSpan":0,"TimeStamp":0,"BeginTime":"","EndTime":"","Snippet":"","PopupInfo":"","HasLabel":-1,"LabelID":0}},
{"type":"Feature","geometry":{"type":"Point","coordinates":[5.349919000000057,50.140224000000046,0,-1.7976931348623157e+308]},"properties":{"Name":"9th AD","FolderPath":"1944-12-27T00:00:01Z","SymbolID":11,"AltMode":-1,"Base":0,"TimeSpan":0,"TimeStamp":0,"BeginTime":"","EndTime":"","Snippet":"","PopupInfo":"","HasLabel":-1,"LabelID":0}},
{"type":"Feature","geometry":{"type":"Point","coordinates":[5.198253000000022,50.12588200000005,0,-1.7976931348623157e+308]},"properties":{"Name":"2nd AD","FolderPath":"1944-12-27T00:00:01Z","SymbolID":11,"AltMode":-1,"Base":0,"TimeSpan":0,"TimeStamp":0,"BeginTime":"","EndTime":"","Snippet":"","PopupInfo":"","HasLabel":-1,"LabelID":0}},
{"type":"Feature","geometry":{"type":"Point","coordinates":[5.491055000000074,49.98798800000003,0,-1.7976931348623157e+308]},"properties":{"Name":"Lehr AD","FolderPath":"1944-12-27T00:00:01Z","SymbolID":11,"AltMode":-1,"Base":0,"TimeSpan":0,"TimeStamp":0,"BeginTime":"","EndTime":"","Snippet":"","PopupInfo":"","HasLabel":-1,"LabelID":0}},
{"type":"Feature","geometry":{"type":"Point","coordinates":[5.618824000000075,49.995389000000046,0,-1.7976931348623157e+308]},"properties":{"Name":"15th ID","FolderPath":"1944-12-27T00:00:01Z","SymbolID":12,"AltMode":-1,"Base":0,"TimeSpan":0,"TimeStamp":0,"BeginTime":"","EndTime":"","Snippet":"","PopupInfo":"","HasLabel":-1,"LabelID":0}},
{"type":"Feature","geometry":{"type":"Point","coordinates":[5.805408000000057,49.93300000000005,0,-1.7976931348623157e+308]},"properties":{"Name":"5th AirD","FolderPath":"1944-12-27T00:00:01Z","SymbolID":13,"AltMode":-1,"Base":0,"TimeSpan":0,"TimeStamp":0,"BeginTime":"","EndTime":"","Snippet":"","PopupInfo":"","HasLabel":-1,"LabelID":0}},
{"type":"Feature","geometry":{"type":"Point","coordinates":[5.797569000000067,49.97069400000004,0,-1.7976931348623157e+308]},"properties":{"Name":"26th ID","FolderPath":"1944-12-27T00:00:01Z","SymbolID":12,"AltMode":-1,"Base":0,"TimeSpan":0,"TimeStamp":0,"BeginTime":"","EndTime":"","Snippet":"","PopupInfo":"","HasLabel":-1,"LabelID":0}},
{"type":"Feature","geometry":{"type":"Point","coordinates":[5.900836000000027,49.91558200000003,0,-1.7976931348623157e+308]},"properties":{"Name":"GD AD","FolderPath":"1944-12-27T00:00:01Z","SymbolID":11,"AltMode":-1,"Base":0,"TimeSpan":0,"TimeStamp":0,"BeginTime":"","EndTime":"","Snippet":"","PopupInfo":"","HasLabel":-1,"LabelID":0}},
{"type":"Feature","geometry":{"type":"Point","coordinates":[6.089063000000067,49.909789000000046,0,-1.7976931348623157e+308]},"properties":{"Name":"79th ID","FolderPath":"1944-12-27T00:00:01Z","SymbolID":12,"AltMode":-1,"Base":0,"TimeSpan":0,"TimeStamp":0,"BeginTime":"","EndTime":"","Snippet":"","PopupInfo":"","HasLabel":-1,"LabelID":0}},
{"type":"Feature","geometry":{"type":"Point","coordinates":[6.22119900000007,49.895065000000045,0,-1.7976931348623157e+308]},"properties":{"Name":"352nd ID","FolderPath":"1944-12-27T00:00:01Z","SymbolID":12,"AltMode":-1,"Base":0,"TimeSpan":0,"TimeStamp":0,"BeginTime":"","EndTime":"","Snippet":"","PopupInfo":"","HasLabel":-1,"LabelID":0}},
{"type":"Feature","geometry":{"type":"Point","coordinates":[6.438621000000069,49.83443200000005,0,-1.7976931348623157e+308]},"properties":{"Name":"276th ID","FolderPath":"1944-12-27T00:00:01Z","SymbolID":12,"AltMode":-1,"Base":0,"TimeSpan":0,"TimeStamp":0,"BeginTime":"","EndTime":"","Snippet":"","PopupInfo":"","HasLabel":-1,"LabelID":0}},
{"type":"Feature","geometry":{"type":"Point","coordinates":[6.608726000000047,49.77520300000003,0,-1.7976931348623157e+308]},"properties":{"Name":"212th ID","FolderPath":"1944-12-27T00:00:01Z","SymbolID":12,"AltMode":-1,"Base":0,"TimeSpan":0,"TimeStamp":0,"BeginTime":"","EndTime":"","Snippet":"","PopupInfo":"","HasLabel":-1,"LabelID":0}},
{"type":"Feature","geometry":{"type":"Point","coordinates":[6.711545000000058,49.586532000000034,0,-1.7976931348623157e+308]},"properties":{"Name":"416th ID","FolderPath":"1944-12-27T00:00:01Z","SymbolID":12,"AltMode":-1,"Base":0,"TimeSpan":0,"TimeStamp":0,"BeginTime":"","EndTime":"","Snippet":"","PopupInfo":"","HasLabel":-1,"LabelID":0}},
{"type":"Feature","geometry":{"type":"Point","coordinates":[6.8143230000000585,49.500582000000065,0,-1.7976931348623157e+308]},"properties":{"Name":"19th ID","FolderPath":"1944-12-27T00:00:01Z","SymbolID":12,"AltMode":-1,"Base":0,"TimeSpan":0,"TimeStamp":0,"BeginTime":"","EndTime":"","Snippet":"","PopupInfo":"","HasLabel":-1,"LabelID":0}},
{"type":"Feature","geometry":{"type":"Point","coordinates":[6.826692000000037,49.44785600000006,0,-1.7976931348623157e+308]},"properties":{"Name":"719th ID","FolderPath":"1944-12-27T00:00:01Z","SymbolID":12,"AltMode":-1,"Base":0,"TimeSpan":0,"TimeStamp":0,"BeginTime":"","EndTime":"","Snippet":"","PopupInfo":"","HasLabel":-1,"LabelID":0}},
{"type":"Feature","geometry":{"type":"Point","coordinates":[6.909935000000075,49.30589000000003,0,-1.7976931348623157e+308]},"properties":{"Name":"36th ID","FolderPath":"1944-12-27T00:00:01Z","SymbolID":12,"AltMode":-1,"Base":0,"TimeSpan":0,"TimeStamp":0,"BeginTime":"","EndTime":"","Snippet":"","PopupInfo":"","HasLabel":-1,"LabelID":0}},
{"type":"Feature","geometry":{"type":"Point","coordinates":[7.156459000000041,49.31801000000007,0,-1.7976931348623157e+308]},"properties":{"Name":"Von Mueller ID","FolderPath":"1944-12-27T00:00:01Z","SymbolID":12,"AltMode":-1,"Base":0,"TimeSpan":0,"TimeStamp":0,"BeginTime":"","EndTime":"","Snippet":"","PopupInfo":"","HasLabel":-1,"LabelID":0}},
{"type":"Feature","geometry":{"type":"Point","coordinates":[7.095223000000033,49.212905000000035,0,-1.7976931348623157e+308]},"properties":{"Name":"347th ID","FolderPath":"1944-12-27T00:00:01Z","SymbolID":12,"AltMode":-1,"Base":0,"TimeSpan":0,"TimeStamp":0,"BeginTime":"","EndTime":"","Snippet":"","PopupInfo":"","HasLabel":-1,"LabelID":0}},
{"type":"Feature","geometry":{"type":"Point","coordinates":[7.25726700000007,49.18911000000003,0,-1.7976931348623157e+308]},"properties":{"Name":"17th SS ID","FolderPath":"1944-12-27T00:00:01Z","SymbolID":12,"AltMode":-1,"Base":0,"TimeSpan":0,"TimeStamp":0,"BeginTime":"","EndTime":"","Snippet":"","PopupInfo":"","HasLabel":-1,"LabelID":0}},
{"type":"Feature","geometry":{"type":"Point","coordinates":[7.373566000000039,49.13768600000003,0,-1.7976931348623157e+308]},"properties":{"Name":"257th ID","FolderPath":"1944-12-27T00:00:01Z","SymbolID":12,"AltMode":-1,"Base":0,"TimeSpan":0,"TimeStamp":0,"BeginTime":"","EndTime":"","Snippet":"","PopupInfo":"","HasLabel":-1,"LabelID":0}},
{"type":"Feature","geometry":{"type":"Point","coordinates":[7.73933100000005,49.235915000000034,0,-1.7976931348623157e+308]},"properties":{"Name":"25th ID (?)","FolderPath":"1944-12-27T00:00:01Z","SymbolID":12,"AltMode":-1,"Base":0,"TimeSpan":0,"TimeStamp":0,"BeginTime":"","EndTime":"","Snippet":"","PopupInfo":"","HasLabel":-1,"LabelID":0}},
{"type":"Feature","geometry":{"type":"Point","coordinates":[7.7149800000000255,49.11328000000003,0,-1.7976931348623157e+308]},"properties":{"Name":"361st ID","FolderPath":"1944-12-27T00:00:01Z","SymbolID":12,"AltMode":-1,"Base":0,"TimeSpan":0,"TimeStamp":0,"BeginTime":"","EndTime":"","Snippet":"","PopupInfo":"","HasLabel":-1,"LabelID":0}},
{"type":"Feature","geometry":{"type":"Point","coordinates":[7.840067000000033,49.22561900000005,0,-1.7976931348623157e+308]},"properties":{"Name":"21st AD (?)","FolderPath":"1944-12-27T00:00:01Z","SymbolID":11,"AltMode":-1,"Base":0,"TimeSpan":0,"TimeStamp":0,"BeginTime":"","EndTime":"","Snippet":"","PopupInfo":"","HasLabel":-1,"LabelID":0}},
{"type":"Feature","geometry":{"type":"Point","coordinates":[7.910873000000038,49.11694200000005,0,-1.7976931348623157e+308]},"properties":{"Name":"245th ID","FolderPath":"1944-12-27T00:00:01Z","SymbolID":12,"AltMode":-1,"Base":0,"TimeSpan":0,"TimeStamp":0,"BeginTime":"","EndTime":"","Snippet":"","PopupInfo":"","HasLabel":-1,"LabelID":0}},
{"type":"Feature","geometry":{"type":"Point","coordinates":[8.103431000000057,49.08251300000006,0,-1.7976931348623157e+308]},"properties":{"Name":"256th ID","FolderPath":"1944-12-27T00:00:01Z","SymbolID":12,"AltMode":-1,"Base":0,"TimeSpan":0,"TimeStamp":0,"BeginTime":"","EndTime":"","Snippet":"","PopupInfo":"","HasLabel":-1,"LabelID":0}},
{"type":"Feature","geometry":{"type":"Point","coordinates":[8.279488000000072,48.89552700000007,0,-1.7976931348623157e+308]},"properties":{"Name":"553rd ID","FolderPath":"1944-12-27T00:00:01Z","SymbolID":12,"AltMode":-1,"Base":0,"TimeSpan":0,"TimeStamp":0,"BeginTime":"","EndTime":"","Snippet":"","PopupInfo":"","HasLabel":-1,"LabelID":0}},
{"type":"Feature","geometry":{"type":"Point","coordinates":[8.391117000000065,48.930738000000076,0,-1.7976931348623157e+308]},"properties":{"Name":"216th ID (?)","FolderPath":"1944-12-27T00:00:01Z","SymbolID":12,"AltMode":-1,"Base":0,"TimeSpan":0,"TimeStamp":0,"BeginTime":"","EndTime":"","Snippet":"","PopupInfo":"","HasLabel":-1,"LabelID":0}},
{"type":"Feature","geometry":{"type":"Point","coordinates":[8.06878400000005,48.32995000000005,0,-1.7976931348623157e+308]},"properties":{"Name":"405th ID","FolderPath":"1944-12-27T00:00:01Z","SymbolID":12,"AltMode":-1,"Base":0,"TimeSpan":0,"TimeStamp":0,"BeginTime":"","EndTime":"","Snippet":"","PopupInfo":"","HasLabel":-1,"LabelID":0}},
{"type":"Feature","geometry":{"type":"Point","coordinates":[7.616632000000038,48.23807900000003,0,-1.7976931348623157e+308]},"properties":{"Name":"198th ID","FolderPath":"1944-12-27T00:00:01Z","SymbolID":12,"AltMode":-1,"Base":0,"TimeSpan":0,"TimeStamp":0,"BeginTime":"","EndTime":"","Snippet":"","PopupInfo":"","HasLabel":-1,"LabelID":0}},
{"type":"Feature","geometry":{"type":"Point","coordinates":[7.57500200000004,48.201681000000065,0,-1.7976931348623157e+308]},"properties":{"Name":"708th ID","FolderPath":"1944-12-27T00:00:01Z","SymbolID":12,"AltMode":-1,"Base":0,"TimeSpan":0,"TimeStamp":0,"BeginTime":"","EndTime":"","Snippet":"","PopupInfo":"","HasLabel":-1,"LabelID":0}},
{"type":"Feature","geometry":{"type":"Point","coordinates":[7.488643000000025,48.15788300000003,0,-1.7976931348623157e+308]},"properties":{"Name":"716th ID","FolderPath":"1944-12-27T00:00:01Z","SymbolID":12,"AltMode":-1,"Base":0,"TimeSpan":0,"TimeStamp":0,"BeginTime":"","EndTime":"","Snippet":"","PopupInfo":"","HasLabel":-1,"LabelID":0}},
{"type":"Feature","geometry":{"type":"Point","coordinates":[7.444247000000075,48.100734000000045,0,-1.7976931348623157e+308]},"properties":{"Name":"16th ID","FolderPath":"1944-12-27T00:00:01Z","SymbolID":12,"AltMode":-1,"Base":0,"TimeSpan":0,"TimeStamp":0,"BeginTime":"","EndTime":"","Snippet":"","PopupInfo":"","HasLabel":-1,"LabelID":0}},
{"type":"Feature","geometry":{"type":"Point","coordinates":[7.349467000000061,48.05998100000005,0,-1.7976931348623157e+308]},"properties":{"Name":"189th ID","FolderPath":"1944-12-27T00:00:01Z","SymbolID":12,"AltMode":-1,"Base":0,"TimeSpan":0,"TimeStamp":0,"BeginTime":"","EndTime":"","Snippet":"","PopupInfo":"","HasLabel":-1,"LabelID":0}},
{"type":"Feature","geometry":{"type":"Point","coordinates":[7.209002000000055,48.02857000000006,0,-1.7976931348623157e+308]},"properties":{"Name":"338th ID","FolderPath":"1944-12-27T00:00:01Z","SymbolID":12,"AltMode":-1,"Base":0,"TimeSpan":0,"TimeStamp":0,"BeginTime":"","EndTime":"","Snippet":"","PopupInfo":"","HasLabel":-1,"LabelID":0}}
]}