{"type":"FeatureCollection", "features": [
{"type":"Feature","geometry":{"type":"Point","coordinates":[4.612209000000064,49.73579100000006,0,-1.7976931348623157e+308]},"properties":{"Name":"28th ID","FolderPath":"1945-01-18T00:00:01Z","SymbolID":0,"AltMode":-1,"Base":0,"TimeSpan":0,"TimeStamp":0,"BeginTime":"","EndTime":"","Snippet":"","PopupInfo":"","HasLabel":-1,"LabelID":0}},
{"type":"Feature","geometry":{"type":"Point","coordinates":[5.576223000000027,50.58428100000003,0,-1.7976931348623157e+308]},"properties":{"Name":"53rd ID","FolderPath":"1945-01-18T00:00:01Z","SymbolID":0,"AltMode":-1,"Base":0,"TimeSpan":0,"TimeStamp":0,"BeginTime":"","EndTime":"","Snippet":"","PopupInfo":"","HasLabel":-1,"LabelID":0}},
{"type":"Feature","geometry":{"type":"Point","coordinates":[5.069209000000058,50.74166000000008,0,-1.7976931348623157e+308]},"properties":{"Name":"GDS AD","FolderPath":"1945-01-18T00:00:01Z","SymbolID":0,"AltMode":-1,"Base":0,"TimeSpan":0,"TimeStamp":0,"BeginTime":"","EndTime":"","Snippet":"","PopupInfo":"","HasLabel":-1,"LabelID":0}},
{"type":"Feature","geometry":{"type":"Point","coordinates":[4.931530000000066,51.63815500000004,0,-1.7976931348623157e+308]},"properties":{"Name":"POL AD","FolderPath":"1945-01-18T00:00:01Z","SymbolID":1,"AltMode":-1,"Base":0,"TimeSpan":0,"TimeStamp":0,"BeginTime":"","EndTime":"","Snippet":"","PopupInfo":"","HasLabel":-1,"LabelID":0}},
{"type":"Feature","geometry":{"type":"Point","coordinates":[5.218153000000029,51.68904800000007,0,-1.7976931348623157e+308]},"properties":{"Name":"4th AD (CDN)","FolderPath":"1945-01-18T00:00:01Z","SymbolID":2,"AltMode":-1,"Base":0,"TimeSpan":0,"TimeStamp":0,"BeginTime":"","EndTime":"","Snippet":"","PopupInfo":"","HasLabel":-1,"LabelID":0}},
{"type":"Feature","geometry":{"type":"Point","coordinates":[5.847984000000054,51.813019000000054,0,-1.7976931348623157e+308]},"properties":{"Name":"3rd ID (CDN)","FolderPath":"1945-01-18T00:00:01Z","SymbolID":3,"AltMode":-1,"Base":0,"TimeSpan":0,"TimeStamp":0,"BeginTime":"","EndTime":"","Snippet":"","PopupInfo":"","HasLabel":-1,"LabelID":0}},
{"type":"Feature","geometry":{"type":"Point","coordinates":[5.7895260000000235,51.877604000000076,0,-1.7976931348623157e+308]},"properties":{"Name":"49th ID","FolderPath":"1945-01-18T00:00:01Z","SymbolID":0,"AltMode":-1,"Base":0,"TimeSpan":0,"TimeStamp":0,"BeginTime":"","EndTime":"","Snippet":"","PopupInfo":"","HasLabel":-1,"LabelID":0}},
{"type":"Feature","geometry":{"type":"Point","coordinates":[5.83186500000005,51.68430900000004,0,-1.7976931348623157e+308]},"properties":{"Name":"2nd ID (CDN)","FolderPath":"1945-01-18T00:00:01Z","SymbolID":3,"AltMode":-1,"Base":0,"TimeSpan":0,"TimeStamp":0,"BeginTime":"","EndTime":"","Snippet":"","PopupInfo":"","HasLabel":-1,"LabelID":0}},
{"type":"Feature","geometry":{"type":"Point","coordinates":[6.027428000000043,51.469531000000075,0,-1.7976931348623157e+308]},"properties":{"Name":"3rd ID","FolderPath":"1945-01-18T00:00:01Z","SymbolID":0,"AltMode":-1,"Base":0,"TimeSpan":0,"TimeStamp":0,"BeginTime":"","EndTime":"","Snippet":"","PopupInfo":"","HasLabel":-1,"LabelID":0}},
{"type":"Feature","geometry":{"type":"Point","coordinates":[5.95052400000003,51.32434400000005,0,-1.7976931348623157e+308]},"properties":{"Name":"15th ID","FolderPath":"1945-01-18T00:00:01Z","SymbolID":0,"AltMode":-1,"Base":0,"TimeSpan":0,"TimeStamp":0,"BeginTime":"","EndTime":"","Snippet":"","PopupInfo":"","HasLabel":-1,"LabelID":0}},
{"type":"Feature","geometry":{"type":"Point","coordinates":[5.819439000000045,51.20895600000006,0,-1.7976931348623157e+308]},"properties":{"Name":"11th AD","FolderPath":"1945-01-18T00:00:01Z","SymbolID":4,"AltMode":-1,"Base":0,"TimeSpan":0,"TimeStamp":0,"BeginTime":"","EndTime":"","Snippet":"","PopupInfo":"","HasLabel":-1,"LabelID":0}},
{"type":"Feature","geometry":{"type":"Point","coordinates":[5.762467000000072,51.04517100000004,0,-1.7976931348623157e+308]},"properties":{"Name":"7th AD","FolderPath":"1945-01-18T00:00:01Z","SymbolID":4,"AltMode":-1,"Base":0,"TimeSpan":0,"TimeStamp":0,"BeginTime":"","EndTime":"","Snippet":"","PopupInfo":"","HasLabel":-1,"LabelID":0}},
{"type":"Feature","geometry":{"type":"Point","coordinates":[5.740966000000071,50.89477700000003,0,-1.7976931348623157e+308]},"properties":{"Name":"52nd ID","FolderPath":"1945-01-18T00:00:01Z","SymbolID":0,"AltMode":-1,"Base":0,"TimeSpan":0,"TimeStamp":0,"BeginTime":"","EndTime":"","Snippet":"","PopupInfo":"","HasLabel":-1,"LabelID":0}},
{"type":"Feature","geometry":{"type":"Point","coordinates":[5.999415000000056,50.95544300000006,0,-1.7976931348623157e+308]},"properties":{"Name":"43rd ID","FolderPath":"1945-01-18T00:00:01Z","SymbolID":0,"AltMode":-1,"Base":0,"TimeSpan":0,"TimeStamp":0,"BeginTime":"","EndTime":"","Snippet":"","PopupInfo":"","HasLabel":-1,"LabelID":0}},
{"type":"Feature","geometry":{"type":"Point","coordinates":[6.19211800000005,50.94369700000004,0,-1.7976931348623157e+308]},"properties":{"Name":"102nd ID","FolderPath":"1945-01-18T00:00:01Z","SymbolID":5,"AltMode":-1,"Base":0,"TimeSpan":0,"TimeStamp":0,"BeginTime":"","EndTime":"","Snippet":"","PopupInfo":"","HasLabel":-1,"LabelID":0}},
{"type":"Feature","geometry":{"type":"Point","coordinates":[6.29158700000005,50.877241000000026,0,-1.7976931348623157e+308]},"properties":{"Name":"29th ID","FolderPath":"1945-01-18T00:00:01Z","SymbolID":5,"AltMode":-1,"Base":0,"TimeSpan":0,"TimeStamp":0,"BeginTime":"","EndTime":"","Snippet":"","PopupInfo":"","HasLabel":-1,"LabelID":0}},
{"type":"Feature","geometry":{"type":"Point","coordinates":[6.338338000000022,50.806197000000054,0,-1.7976931348623157e+308]},"properties":{"Name":"104th ID","FolderPath":"1945-01-18T00:00:01Z","SymbolID":5,"AltMode":-1,"Base":0,"TimeSpan":0,"TimeStamp":0,"BeginTime":"","EndTime":"","Snippet":"","PopupInfo":"","HasLabel":-1,"LabelID":0}},
{"type":"Feature","geometry":{"type":"Point","coordinates":[6.350485000000049,50.70281200000005,0,-1.7976931348623157e+308]},"properties":{"Name":"8th ID","FolderPath":"1945-01-18T00:00:01Z","SymbolID":5,"AltMode":-1,"Base":0,"TimeSpan":0,"TimeStamp":0,"BeginTime":"","EndTime":"","Snippet":"","PopupInfo":"","HasLabel":-1,"LabelID":0}},
{"type":"Feature","geometry":{"type":"Point","coordinates":[5.957133000000056,50.60559600000005,0,-1.7976931348623157e+308]},"properties":{"Name":"5th AD","FolderPath":"1945-01-18T00:00:01Z","SymbolID":6,"AltMode":-1,"Base":0,"TimeSpan":0,"TimeStamp":0,"BeginTime":"","EndTime":"","Snippet":"","PopupInfo":"","HasLabel":-1,"LabelID":0}},
{"type":"Feature","geometry":{"type":"Point","coordinates":[6.207269000000053,50.63353900000004,0,-1.7976931348623157e+308]},"properties":{"Name":"78th ID","FolderPath":"1945-01-18T00:00:01Z","SymbolID":5,"AltMode":-1,"Base":0,"TimeSpan":0,"TimeStamp":0,"BeginTime":"","EndTime":"","Snippet":"","PopupInfo":"","HasLabel":-1,"LabelID":0}},
{"type":"Feature","geometry":{"type":"Point","coordinates":[5.838326000000052,50.47735800000004,0,-1.7976931348623157e+308]},"properties":{"Name":"82nd AB","FolderPath":"1945-01-18T00:00:01Z","SymbolID":7,"AltMode":-1,"Base":0,"TimeSpan":0,"TimeStamp":0,"BeginTime":"","EndTime":"","Snippet":"","PopupInfo":"","HasLabel":-1,"LabelID":0}},
{"type":"Feature","geometry":{"type":"Point","coordinates":[5.790660000000059,50.52186300000005,0,-1.7976931348623157e+308]},"properties":{"Name":"7th AD","FolderPath":"1945-01-18T00:00:01Z","SymbolID":6,"AltMode":-1,"Base":0,"TimeSpan":0,"TimeStamp":0,"BeginTime":"","EndTime":"","Snippet":"","PopupInfo":"","HasLabel":-1,"LabelID":0}},
{"type":"Feature","geometry":{"type":"Point","coordinates":[5.51236700000004,50.31424100000004,0,-1.7976931348623157e+308]},"properties":{"Name":"84th ID","FolderPath":"1945-01-18T00:00:01Z","SymbolID":5,"AltMode":-1,"Base":0,"TimeSpan":0,"TimeStamp":0,"BeginTime":"","EndTime":"","Snippet":"","PopupInfo":"","HasLabel":-1,"LabelID":0}},
{"type":"Feature","geometry":{"type":"Point","coordinates":[5.399527000000035,50.20032700000007,0,-1.7976931348623157e+308]},"properties":{"Name":"51st ID","FolderPath":"1945-01-18T00:00:01Z","SymbolID":5,"AltMode":-1,"Base":0,"TimeSpan":0,"TimeStamp":0,"BeginTime":"","EndTime":"","Snippet":"","PopupInfo":"","HasLabel":-1,"LabelID":0}},
{"type":"Feature","geometry":{"type":"Point","coordinates":[5.3740830000000415,50.13519000000008,0,-1.7976931348623157e+308]},"properties":{"Name":"6th AD","FolderPath":"1945-01-18T00:00:01Z","SymbolID":6,"AltMode":-1,"Base":0,"TimeSpan":0,"TimeStamp":0,"BeginTime":"","EndTime":"","Snippet":"","PopupInfo":"","HasLabel":-1,"LabelID":0}},
{"type":"Feature","geometry":{"type":"Point","coordinates":[5.780880000000025,49.951850000000036,0,-1.7976931348623157e+308]},"properties":{"Name":"4th AD","FolderPath":"1945-01-18T00:00:01Z","SymbolID":6,"AltMode":-1,"Base":0,"TimeSpan":0,"TimeStamp":0,"BeginTime":"","EndTime":"","Snippet":"","PopupInfo":"","HasLabel":-1,"LabelID":0}},
{"type":"Feature","geometry":{"type":"Point","coordinates":[5.817894000000024,49.984529000000066,0,-1.7976931348623157e+308]},"properties":{"Name":"90th ID","FolderPath":"1945-01-18T00:00:01Z","SymbolID":5,"AltMode":-1,"Base":0,"TimeSpan":0,"TimeStamp":0,"BeginTime":"","EndTime":"","Snippet":"","PopupInfo":"","HasLabel":-1,"LabelID":0}},
{"type":"Feature","geometry":{"type":"Point","coordinates":[5.696676000000025,50.02716200000003,0,-1.7976931348623157e+308]},"properties":{"Name":"101st AB","FolderPath":"1945-01-18T00:00:01Z","SymbolID":8,"AltMode":-1,"Base":0,"TimeSpan":0,"TimeStamp":0,"BeginTime":"","EndTime":"","Snippet":"","PopupInfo":"","HasLabel":-1,"LabelID":0}},
{"type":"Feature","geometry":{"type":"Point","coordinates":[5.815063000000066,50.02786900000007,0,-1.7976931348623157e+308]},"properties":{"Name":"6th AD","FolderPath":"1945-01-18T00:00:01Z","SymbolID":6,"AltMode":-1,"Base":0,"TimeSpan":0,"TimeStamp":0,"BeginTime":"","EndTime":"","Snippet":"","PopupInfo":"","HasLabel":-1,"LabelID":0}},
{"type":"Feature","geometry":{"type":"Point","coordinates":[5.725120000000061,50.06638500000008,0,-1.7976931348623157e+308]},"properties":{"Name":"11th AD","FolderPath":"1945-01-18T00:00:01Z","SymbolID":6,"AltMode":-1,"Base":0,"TimeSpan":0,"TimeStamp":0,"BeginTime":"","EndTime":"","Snippet":"","PopupInfo":"","HasLabel":-1,"LabelID":0}},
{"type":"Feature","geometry":{"type":"Point","coordinates":[5.71748400000007,50.10469000000006,0,-1.7976931348623157e+308]},"properties":{"Name":"17th AB","FolderPath":"1945-01-18T00:00:01Z","SymbolID":9,"AltMode":-1,"Base":0,"TimeSpan":0,"TimeStamp":0,"BeginTime":"","EndTime":"","Snippet":"","PopupInfo":"","HasLabel":-1,"LabelID":0}},
{"type":"Feature","geometry":{"type":"Point","coordinates":[5.76135800000003,50.17244100000005,0,-1.7976931348623157e+308]},"properties":{"Name":"2nd AD","FolderPath":"1945-01-18T00:00:01Z","SymbolID":6,"AltMode":-1,"Base":0,"TimeSpan":0,"TimeStamp":0,"BeginTime":"","EndTime":"","Snippet":"","PopupInfo":"","HasLabel":-1,"LabelID":0}},
{"type":"Feature","geometry":{"type":"Point","coordinates":[5.8269990000000575,50.21560900000003,0,-1.7976931348623157e+308]},"properties":{"Name":"3rd AD","FolderPath":"1945-01-18T00:00:01Z","SymbolID":6,"AltMode":-1,"Base":0,"TimeSpan":0,"TimeStamp":0,"BeginTime":"","EndTime":"","Snippet":"","PopupInfo":"","HasLabel":-1,"LabelID":0}},
{"type":"Feature","geometry":{"type":"Point","coordinates":[5.823056000000065,50.25080400000007,0,-1.7976931348623157e+308]},"properties":{"Name":"83rd ID","FolderPath":"1945-01-18T00:00:01Z","SymbolID":5,"AltMode":-1,"Base":0,"TimeSpan":0,"TimeStamp":0,"BeginTime":"","EndTime":"","Snippet":"","PopupInfo":"","HasLabel":-1,"LabelID":0}},
{"type":"Feature","geometry":{"type":"Point","coordinates":[5.8808740000000626,50.29741500000006,0,-1.7976931348623157e+308]},"properties":{"Name":"75th ID","FolderPath":"1945-01-18T00:00:01Z","SymbolID":5,"AltMode":-1,"Base":0,"TimeSpan":0,"TimeStamp":0,"BeginTime":"","EndTime":"","Snippet":"","PopupInfo":"","HasLabel":-1,"LabelID":0}},
{"type":"Feature","geometry":{"type":"Point","coordinates":[5.9173150000000305,50.35042500000003,0,-1.7976931348623157e+308]},"properties":{"Name":"106th ID","FolderPath":"1945-01-18T00:00:01Z","SymbolID":5,"AltMode":-1,"Base":0,"TimeSpan":0,"TimeStamp":0,"BeginTime":"","EndTime":"","Snippet":"","PopupInfo":"","HasLabel":-1,"LabelID":0}},
{"type":"Feature","geometry":{"type":"Point","coordinates":[6.05535500000002,50.37991500000004,0,-1.7976931348623157e+308]},"properties":{"Name":"30th ID","FolderPath":"1945-01-18T00:00:01Z","SymbolID":5,"AltMode":-1,"Base":0,"TimeSpan":0,"TimeStamp":0,"BeginTime":"","EndTime":"","Snippet":"","PopupInfo":"","HasLabel":-1,"LabelID":0}},
{"type":"Feature","geometry":{"type":"Point","coordinates":[6.224852000000055,50.41898800000007,0,-1.7976931348623157e+308]},"properties":{"Name":"2nd ID","FolderPath":"1945-01-18T00:00:01Z","SymbolID":5,"AltMode":-1,"Base":0,"TimeSpan":0,"TimeStamp":0,"BeginTime":"","EndTime":"","Snippet":"","PopupInfo":"","HasLabel":-1,"LabelID":0}},
{"type":"Feature","geometry":{"type":"Point","coordinates":[6.187364000000059,50.45016600000008,0,-1.7976931348623157e+308]},"properties":{"Name":"1st ID","FolderPath":"1945-01-18T00:00:01Z","SymbolID":5,"AltMode":-1,"Base":0,"TimeSpan":0,"TimeStamp":0,"BeginTime":"","EndTime":"","Snippet":"","PopupInfo":"","HasLabel":-1,"LabelID":0}},
{"type":"Feature","geometry":{"type":"Point","coordinates":[6.205171000000064,50.486912000000075,0,-1.7976931348623157e+308]},"properties":{"Name":"99th ID","FolderPath":"1945-01-18T00:00:01Z","SymbolID":5,"AltMode":-1,"Base":0,"TimeSpan":0,"TimeStamp":0,"BeginTime":"","EndTime":"","Snippet":"","PopupInfo":"","HasLabel":-1,"LabelID":0}},
{"type":"Feature","geometry":{"type":"Point","coordinates":[6.179415000000063,50.52962800000006,0,-1.7976931348623157e+308]},"properties":{"Name":"9th ID","FolderPath":"1945-01-18T00:00:01Z","SymbolID":5,"AltMode":-1,"Base":0,"TimeSpan":0,"TimeStamp":0,"BeginTime":"","EndTime":"","Snippet":"","PopupInfo":"","HasLabel":-1,"LabelID":0}},
{"type":"Feature","geometry":{"type":"Point","coordinates":[5.7802240000000324,49.87399000000005,0,-1.7976931348623157e+308]},"properties":{"Name":"35th ID","FolderPath":"1945-01-18T00:00:01Z","SymbolID":5,"AltMode":-1,"Base":0,"TimeSpan":0,"TimeStamp":0,"BeginTime":"","EndTime":"","Snippet":"","PopupInfo":"","HasLabel":-1,"LabelID":0}},
{"type":"Feature","geometry":{"type":"Point","coordinates":[5.9148420000000215,49.90019700000005,0,-1.7976931348623157e+308]},"properties":{"Name":"26th ID","FolderPath":"1945-01-18T00:00:01Z","SymbolID":5,"AltMode":-1,"Base":0,"TimeSpan":0,"TimeStamp":0,"BeginTime":"","EndTime":"","Snippet":"","PopupInfo":"","HasLabel":-1,"LabelID":0}},
{"type":"Feature","geometry":{"type":"Point","coordinates":[6.054110000000037,49.824245000000076,0,-1.7976931348623157e+308]},"properties":{"Name":"80th ID","FolderPath":"1945-01-18T00:00:01Z","SymbolID":5,"AltMode":-1,"Base":0,"TimeSpan":0,"TimeStamp":0,"BeginTime":"","EndTime":"","Snippet":"","PopupInfo":"","HasLabel":-1,"LabelID":0}},
{"type":"Feature","geometry":{"type":"Point","coordinates":[6.182648000000029,49.82603000000006,0,-1.7976931348623157e+308]},"properties":{"Name":"5th ID","FolderPath":"1945-01-18T00:00:01Z","SymbolID":5,"AltMode":-1,"Base":0,"TimeSpan":0,"TimeStamp":0,"BeginTime":"","EndTime":"","Snippet":"","PopupInfo":"","HasLabel":-1,"LabelID":0}},
{"type":"Feature","geometry":{"type":"Point","coordinates":[6.293989000000067,49.80685100000005,0,-1.7976931348623157e+308]},"properties":{"Name":"4th ID","FolderPath":"1945-01-18T00:00:01Z","SymbolID":5,"AltMode":-1,"Base":0,"TimeSpan":0,"TimeStamp":0,"BeginTime":"","EndTime":"","Snippet":"","PopupInfo":"","HasLabel":-1,"LabelID":0}},
{"type":"Feature","geometry":{"type":"Point","coordinates":[6.405259000000058,49.751540000000034,0,-1.7976931348623157e+308]},"properties":{"Name":"87th ID","FolderPath":"1945-01-18T00:00:01Z","SymbolID":5,"AltMode":-1,"Base":0,"TimeSpan":0,"TimeStamp":0,"BeginTime":"","EndTime":"","Snippet":"","PopupInfo":"","HasLabel":-1,"LabelID":0}},
{"type":"Feature","geometry":{"type":"Point","coordinates":[6.464707000000033,49.45655100000005,0,-1.7976931348623157e+308]},"properties":{"Name":"94th ID","FolderPath":"1945-01-18T00:00:01Z","SymbolID":5,"AltMode":-1,"Base":0,"TimeSpan":0,"TimeStamp":0,"BeginTime":"","EndTime":"","Snippet":"","PopupInfo":"","HasLabel":-1,"LabelID":0}},
{"type":"Feature","geometry":{"type":"Point","coordinates":[6.653656000000069,49.28194300000007,0,-1.7976931348623157e+308]},"properties":{"Name":"95th ID","FolderPath":"1945-01-18T00:00:01Z","SymbolID":5,"AltMode":-1,"Base":0,"TimeSpan":0,"TimeStamp":0,"BeginTime":"","EndTime":"","Snippet":"","PopupInfo":"","HasLabel":-1,"LabelID":0}},
{"type":"Feature","geometry":{"type":"Point","coordinates":[6.280527000000063,49.259686000000045,0,-1.7976931348623157e+308]},"properties":{"Name":"9th AD","FolderPath":"1945-01-18T00:00:01Z","SymbolID":6,"AltMode":-1,"Base":0,"TimeSpan":0,"TimeStamp":0,"BeginTime":"","EndTime":"","Snippet":"","PopupInfo":"","HasLabel":-1,"LabelID":0}},
{"type":"Feature","geometry":{"type":"Point","coordinates":[6.2370480000000725,49.08112300000005,0,-1.7976931348623157e+308]},"properties":{"Name":"10th AD","FolderPath":"1945-01-18T00:00:01Z","SymbolID":6,"AltMode":-1,"Base":0,"TimeSpan":0,"TimeStamp":0,"BeginTime":"","EndTime":"","Snippet":"","PopupInfo":"","HasLabel":-1,"LabelID":0}},
{"type":"Feature","geometry":{"type":"Point","coordinates":[5.989634000000024,48.88687800000008,0,-1.7976931348623157e+308]},"properties":{"Name":"8th AD","FolderPath":"1945-01-18T00:00:01Z","SymbolID":6,"AltMode":-1,"Base":0,"TimeSpan":0,"TimeStamp":0,"BeginTime":"","EndTime":"","Snippet":"","PopupInfo":"","HasLabel":-1,"LabelID":0}},
{"type":"Feature","geometry":{"type":"Point","coordinates":[6.865933000000041,49.122160000000065,0,-1.7976931348623157e+308]},"properties":{"Name":"70th ID","FolderPath":"1945-01-18T00:00:01Z","SymbolID":5,"AltMode":-1,"Base":0,"TimeSpan":0,"TimeStamp":0,"BeginTime":"","EndTime":"","Snippet":"","PopupInfo":"","HasLabel":-1,"LabelID":0}},
{"type":"Feature","geometry":{"type":"Point","coordinates":[7.06680700000004,49.07520200000005,0,-1.7976931348623157e+308]},"properties":{"Name":"44th ID","FolderPath":"1945-01-18T00:00:01Z","SymbolID":5,"AltMode":-1,"Base":0,"TimeSpan":0,"TimeStamp":0,"BeginTime":"","EndTime":"","Snippet":"","PopupInfo":"","HasLabel":-1,"LabelID":0}},
{"type":"Feature","geometry":{"type":"Point","coordinates":[7.10690100000005,48.83699000000007,0,-1.7976931348623157e+308]},"properties":{"Name":"2nd AD (FR)","FolderPath":"1945-01-18T00:00:01Z","SymbolID":10,"AltMode":-1,"Base":0,"TimeSpan":0,"TimeStamp":0,"BeginTime":"","EndTime":"","Snippet":"","PopupInfo":"","HasLabel":-1,"LabelID":0}},
{"type":"Feature","geometry":{"type":"Point","coordinates":[7.167939000000047,48.96323600000005,0,-1.7976931348623157e+308]},"properties":{"Name":"63rd ID","FolderPath":"1945-01-18T00:00:01Z","SymbolID":5,"AltMode":-1,"Base":0,"TimeSpan":0,"TimeStamp":0,"BeginTime":"","EndTime":"","Snippet":"","PopupInfo":"","HasLabel":-1,"LabelID":0}},
{"type":"Feature","geometry":{"type":"Point","coordinates":[7.244074000000069,48.99799400000006,0,-1.7976931348623157e+308]},"properties":{"Name":"36th ID","FolderPath":"1945-01-18T00:00:01Z","SymbolID":5,"AltMode":-1,"Base":0,"TimeSpan":0,"TimeStamp":0,"BeginTime":"","EndTime":"","Snippet":"","PopupInfo":"","HasLabel":-1,"LabelID":0}},
{"type":"Feature","geometry":{"type":"Point","coordinates":[7.276160000000061,49.04758300000003,0,-1.7976931348623157e+308]},"properties":{"Name":"100th ID","FolderPath":"1945-01-18T00:00:01Z","SymbolID":5,"AltMode":-1,"Base":0,"TimeSpan":0,"TimeStamp":0,"BeginTime":"","EndTime":"","Snippet":"","PopupInfo":"","HasLabel":-1,"LabelID":0}},
{"type":"Feature","geometry":{"type":"Point","coordinates":[7.473326000000043,48.894944000000066,0,-1.7976931348623157e+308]},"properties":{"Name":"45th ID","FolderPath":"1945-01-18T00:00:01Z","SymbolID":5,"AltMode":-1,"Base":0,"TimeSpan":0,"TimeStamp":0,"BeginTime":"","EndTime":"","Snippet":"","PopupInfo":"","HasLabel":-1,"LabelID":0}},
{"type":"Feature","geometry":{"type":"Point","coordinates":[7.567837000000054,48.934547000000066,0,-1.7976931348623157e+308]},"properties":{"Name":"103rd ID","FolderPath":"1945-01-18T00:00:01Z","SymbolID":5,"AltMode":-1,"Base":0,"TimeSpan":0,"TimeStamp":0,"BeginTime":"","EndTime":"","Snippet":"","PopupInfo":"","HasLabel":-1,"LabelID":0}},
{"type":"Feature","geometry":{"type":"Point","coordinates":[7.825663000000077,48.935223000000065,0,-1.7976931348623157e+308]},"properties":{"Name":"14th AD","FolderPath":"1945-01-18T00:00:01Z","SymbolID":6,"AltMode":-1,"Base":0,"TimeSpan":0,"TimeStamp":0,"BeginTime":"","EndTime":"","Snippet":"","PopupInfo":"","HasLabel":-1,"LabelID":0}},
{"type":"Feature","geometry":{"type":"Point","coordinates":[7.871349000000066,48.86709200000007,0,-1.7976931348623157e+308]},"properties":{"Name":"79th ID","FolderPath":"1945-01-18T00:00:01Z","SymbolID":5,"AltMode":-1,"Base":0,"TimeSpan":0,"TimeStamp":0,"BeginTime":"","EndTime":"","Snippet":"","PopupInfo":"","HasLabel":-1,"LabelID":0}},
{"type":"Feature","geometry":{"type":"Point","coordinates":[7.769706000000042,48.78196500000007,0,-1.7976931348623157e+308]},"properties":{"Name":"12th AD","FolderPath":"1945-01-18T00:00:01Z","SymbolID":6,"AltMode":-1,"Base":0,"TimeSpan":0,"TimeStamp":0,"BeginTime":"","EndTime":"","Snippet":"","PopupInfo":"","HasLabel":-1,"LabelID":0}},
{"type":"Feature","geometry":{"type":"Point","coordinates":[7.7551200000000335,48.71503700000005,0,-1.7976931348623157e+308]},"properties":{"Name":"42nd ID","FolderPath":"1945-01-18T00:00:01Z","SymbolID":5,"AltMode":-1,"Base":0,"TimeSpan":0,"TimeStamp":0,"BeginTime":"","EndTime":"","Snippet":"","PopupInfo":"","HasLabel":-1,"LabelID":0}},
{"type":"Feature","geometry":{"type":"Point","coordinates":[7.749486000000047,48.65189000000004,0,-1.7976931348623157e+308]},"properties":{"Name":"3rd ID (ALG)","FolderPath":"1945-01-18T00:00:01Z","SymbolID":11,"AltMode":-1,"Base":0,"TimeSpan":0,"TimeStamp":0,"BeginTime":"","EndTime":"","Snippet":"","PopupInfo":"","HasLabel":-1,"LabelID":0}},
{"type":"Feature","geometry":{"type":"Point","coordinates":[7.413801000000035,48.29901300000006,0,-1.7976931348623157e+308]},"properties":{"Name":"1st ID (FR)","FolderPath":"1945-01-18T00:00:01Z","SymbolID":12,"AltMode":-1,"Base":0,"TimeSpan":0,"TimeStamp":0,"BeginTime":"","EndTime":"","Snippet":"","PopupInfo":"","HasLabel":-1,"LabelID":0}},
{"type":"Feature","geometry":{"type":"Point","coordinates":[7.192701000000056,48.13687900000008,0,-1.7976931348623157e+308]},"properties":{"Name":"3rd ID","FolderPath":"1945-01-18T00:00:01Z","SymbolID":5,"AltMode":-1,"Base":0,"TimeSpan":0,"TimeStamp":0,"BeginTime":"","EndTime":"","Snippet":"","PopupInfo":"","HasLabel":-1,"LabelID":0}},
{"type":"Feature","geometry":{"type":"Point","coordinates":[7.040858000000071,48.19656500000008,0,-1.7976931348623157e+308]},"properties":{"Name":"5th AD (FR)","FolderPath":"1945-01-18T00:00:01Z","SymbolID":10,"AltMode":-1,"Base":0,"TimeSpan":0,"TimeStamp":0,"BeginTime":"","EndTime":"","Snippet":"","PopupInfo":"","HasLabel":-1,"LabelID":0}},
{"type":"Feature","geometry":{"type":"Point","coordinates":[4.372612000000061,51.71646000000004,0,-1.7976931348623157e+308]},"properties":{"Name":"346th ID","FolderPath":"1945-01-18T00:00:01Z","SymbolID":13,"AltMode":-1,"Base":0,"TimeSpan":0,"TimeStamp":0,"BeginTime":"","EndTime":"","Snippet":"","PopupInfo":"","HasLabel":-1,"LabelID":0}},
{"type":"Feature","geometry":{"type":"Point","coordinates":[5.008444000000054,51.90896300000003,0,-1.7976931348623157e+308]},"properties":{"Name":"712th ID","FolderPath":"1945-01-18T00:00:01Z","SymbolID":13,"AltMode":-1,"Base":0,"TimeSpan":0,"TimeStamp":0,"BeginTime":"","EndTime":"","Snippet":"","PopupInfo":"","HasLabel":-1,"LabelID":0}},
{"type":"Feature","geometry":{"type":"Point","coordinates":[4.997107000000028,51.77133200000003,0,-1.7976931348623157e+308]},"properties":{"Name":"6th AirD","FolderPath":"1945-01-18T00:00:01Z","SymbolID":14,"AltMode":-1,"Base":0,"TimeSpan":0,"TimeStamp":0,"BeginTime":"","EndTime":"","Snippet":"","PopupInfo":"","HasLabel":-1,"LabelID":0}},
{"type":"Feature","geometry":{"type":"Point","coordinates":[5.866751000000022,51.939103000000046,0,-1.7976931348623157e+308]},"properties":{"Name":"2nd AirD","FolderPath":"1945-01-18T00:00:01Z","SymbolID":14,"AltMode":-1,"Base":0,"TimeSpan":0,"TimeStamp":0,"BeginTime":"","EndTime":"","Snippet":"","PopupInfo":"","HasLabel":-1,"LabelID":0}},
{"type":"Feature","geometry":{"type":"Point","coordinates":[6.513826000000051,51.79688800000008,0,-1.7976931348623157e+308]},"properties":{"Name":"8th AirD (?)","FolderPath":"1945-01-18T00:00:01Z","SymbolID":14,"AltMode":-1,"Base":0,"TimeSpan":0,"TimeStamp":0,"BeginTime":"","EndTime":"","Snippet":"","PopupInfo":"","HasLabel":-1,"LabelID":0}},
{"type":"Feature","geometry":{"type":"Point","coordinates":[6.145452000000034,51.72163400000005,0,-1.7976931348623157e+308]},"properties":{"Name":"84th ID","FolderPath":"1945-01-18T00:00:01Z","SymbolID":13,"AltMode":-1,"Base":0,"TimeSpan":0,"TimeStamp":0,"BeginTime":"","EndTime":"","Snippet":"","PopupInfo":"","HasLabel":-1,"LabelID":0}},
{"type":"Feature","geometry":{"type":"Point","coordinates":[6.166108000000065,51.629567000000065,0,-1.7976931348623157e+308]},"properties":{"Name":"190th ID","FolderPath":"1945-01-18T00:00:01Z","SymbolID":13,"AltMode":-1,"Base":0,"TimeSpan":0,"TimeStamp":0,"BeginTime":"","EndTime":"","Snippet":"","PopupInfo":"","HasLabel":-1,"LabelID":0}},
{"type":"Feature","geometry":{"type":"Point","coordinates":[6.219222000000059,51.56692300000003,0,-1.7976931348623157e+308]},"properties":{"Name":"406th ID","FolderPath":"1945-01-18T00:00:01Z","SymbolID":13,"AltMode":-1,"Base":0,"TimeSpan":0,"TimeStamp":0,"BeginTime":"","EndTime":"","Snippet":"","PopupInfo":"","HasLabel":-1,"LabelID":0}},
{"type":"Feature","geometry":{"type":"Point","coordinates":[6.269710000000032,51.40734500000008,0,-1.7976931348623157e+308]},"properties":{"Name":"180th ID","FolderPath":"1945-01-18T00:00:01Z","SymbolID":13,"AltMode":-1,"Base":0,"TimeSpan":0,"TimeStamp":0,"BeginTime":"","EndTime":"","Snippet":"","PopupInfo":"","HasLabel":-1,"LabelID":0}},
{"type":"Feature","geometry":{"type":"Point","coordinates":[6.080028000000027,51.19737200000003,0,-1.7976931348623157e+308]},"properties":{"Name":"606th ZBV ID","FolderPath":"1945-01-18T00:00:01Z","SymbolID":13,"AltMode":-1,"Base":0,"TimeSpan":0,"TimeStamp":0,"BeginTime":"","EndTime":"","Snippet":"","PopupInfo":"","HasLabel":-1,"LabelID":0}},
{"type":"Feature","geometry":{"type":"Point","coordinates":[5.96525500000007,51.06444400000004,0,-1.7976931348623157e+308]},"properties":{"Name":"176th ID","FolderPath":"1945-01-18T00:00:01Z","SymbolID":13,"AltMode":-1,"Base":0,"TimeSpan":0,"TimeStamp":0,"BeginTime":"","EndTime":"","Snippet":"","PopupInfo":"","HasLabel":-1,"LabelID":0}},
{"type":"Feature","geometry":{"type":"Point","coordinates":[6.2070960000000355,51.01897700000006,0,-1.7976931348623157e+308]},"properties":{"Name":"183rd ID","FolderPath":"1945-01-18T00:00:01Z","SymbolID":13,"AltMode":-1,"Base":0,"TimeSpan":0,"TimeStamp":0,"BeginTime":"","EndTime":"","Snippet":"","PopupInfo":"","HasLabel":-1,"LabelID":0}},
{"type":"Feature","geometry":{"type":"Point","coordinates":[6.327132000000063,50.98706500000003,0,-1.7976931348623157e+308]},"properties":{"Name":"59th ID","FolderPath":"1945-01-18T00:00:01Z","SymbolID":13,"AltMode":-1,"Base":0,"TimeSpan":0,"TimeStamp":0,"BeginTime":"","EndTime":"","Snippet":"","PopupInfo":"","HasLabel":-1,"LabelID":0}},
{"type":"Feature","geometry":{"type":"Point","coordinates":[6.527513000000056,50.83494500000006,0,-1.7976931348623157e+308]},"properties":{"Name":"363rd ID","FolderPath":"1945-01-18T00:00:01Z","SymbolID":13,"AltMode":-1,"Base":0,"TimeSpan":0,"TimeStamp":0,"BeginTime":"","EndTime":"","Snippet":"","PopupInfo":"","HasLabel":-1,"LabelID":0}},
{"type":"Feature","geometry":{"type":"Point","coordinates":[6.9156410000000506,50.841874000000075,0,-1.7976931348623157e+308]},"properties":{"Name":"275th ID","FolderPath":"1945-01-18T00:00:01Z","SymbolID":13,"AltMode":-1,"Base":0,"TimeSpan":0,"TimeStamp":0,"BeginTime":"","EndTime":"","Snippet":"","PopupInfo":"","HasLabel":-1,"LabelID":0}},
{"type":"Feature","geometry":{"type":"Point","coordinates":[6.735233000000051,50.802951000000064,0,-1.7976931348623157e+308]},"properties":{"Name":"47th ID","FolderPath":"1945-01-18T00:00:01Z","SymbolID":13,"AltMode":-1,"Base":0,"TimeSpan":0,"TimeStamp":0,"BeginTime":"","EndTime":"","Snippet":"","PopupInfo":"","HasLabel":-1,"LabelID":0}},
{"type":"Feature","geometry":{"type":"Point","coordinates":[6.523550000000057,50.67512500000004,0,-1.7976931348623157e+308]},"properties":{"Name":"85th ID","FolderPath":"1945-01-18T00:00:01Z","SymbolID":13,"AltMode":-1,"Base":0,"TimeSpan":0,"TimeStamp":0,"BeginTime":"","EndTime":"","Snippet":"","PopupInfo":"","HasLabel":-1,"LabelID":0}},
{"type":"Feature","geometry":{"type":"Point","coordinates":[6.7614090000000715,50.715224000000035,0,-1.7976931348623157e+308]},"properties":{"Name":"353rd ID","FolderPath":"1945-01-18T00:00:01Z","SymbolID":13,"AltMode":-1,"Base":0,"TimeSpan":0,"TimeStamp":0,"BeginTime":"","EndTime":"","Snippet":"","PopupInfo":"","HasLabel":-1,"LabelID":0}},
{"type":"Feature","geometry":{"type":"Point","coordinates":[6.389458000000047,50.49956700000007,0,-1.7976931348623157e+308]},"properties":{"Name":"246th ID","FolderPath":"1945-01-18T00:00:01Z","SymbolID":13,"AltMode":-1,"Base":0,"TimeSpan":0,"TimeStamp":0,"BeginTime":"","EndTime":"","Snippet":"","PopupInfo":"","HasLabel":-1,"LabelID":0}},
{"type":"Feature","geometry":{"type":"Point","coordinates":[6.393025000000023,50.548748000000046,0,-1.7976931348623157e+308]},"properties":{"Name":"272nd ID","FolderPath":"1945-01-18T00:00:01Z","SymbolID":13,"AltMode":-1,"Base":0,"TimeSpan":0,"TimeStamp":0,"BeginTime":"","EndTime":"","Snippet":"","PopupInfo":"","HasLabel":-1,"LabelID":0}},
{"type":"Feature","geometry":{"type":"Point","coordinates":[6.11478100000005,49.88428400000004,0,-1.7976931348623157e+308]},"properties":{"Name":"276th ID","FolderPath":"1945-01-18T00:00:01Z","SymbolID":13,"AltMode":-1,"Base":0,"TimeSpan":0,"TimeStamp":0,"BeginTime":"","EndTime":"","Snippet":"","PopupInfo":"","HasLabel":-1,"LabelID":0}},
{"type":"Feature","geometry":{"type":"Point","coordinates":[6.087337000000048,49.91579000000007,0,-1.7976931348623157e+308]},"properties":{"Name":"9th ID","FolderPath":"1945-01-18T00:00:01Z","SymbolID":13,"AltMode":-1,"Base":0,"TimeSpan":0,"TimeStamp":0,"BeginTime":"","EndTime":"","Snippet":"","PopupInfo":"","HasLabel":-1,"LabelID":0}},
{"type":"Feature","geometry":{"type":"Point","coordinates":[6.059706000000062,49.94657900000004,0,-1.7976931348623157e+308]},"properties":{"Name":"5th AirD","FolderPath":"1945-01-18T00:00:01Z","SymbolID":14,"AltMode":-1,"Base":0,"TimeSpan":0,"TimeStamp":0,"BeginTime":"","EndTime":"","Snippet":"","PopupInfo":"","HasLabel":-1,"LabelID":0}},
{"type":"Feature","geometry":{"type":"Point","coordinates":[5.99317300000007,49.96837900000003,0,-1.7976931348623157e+308]},"properties":{"Name":"1st SS AD","FolderPath":"1945-01-18T00:00:01Z","SymbolID":15,"AltMode":-1,"Base":0,"TimeSpan":0,"TimeStamp":0,"BeginTime":"","EndTime":"","Snippet":"","PopupInfo":"","HasLabel":-1,"LabelID":0}},
{"type":"Feature","geometry":{"type":"Point","coordinates":[5.950305000000071,49.99645400000003,0,-1.7976931348623157e+308]},"properties":{"Name":"167th ID","FolderPath":"1945-01-18T00:00:01Z","SymbolID":13,"AltMode":-1,"Base":0,"TimeSpan":0,"TimeStamp":0,"BeginTime":"","EndTime":"","Snippet":"","PopupInfo":"","HasLabel":-1,"LabelID":0}},
{"type":"Feature","geometry":{"type":"Point","coordinates":[5.94685800000002,50.026808000000074,0,-1.7976931348623157e+308]},"properties":{"Name":"340th ID","FolderPath":"1945-01-18T00:00:01Z","SymbolID":13,"AltMode":-1,"Base":0,"TimeSpan":0,"TimeStamp":0,"BeginTime":"","EndTime":"","Snippet":"","PopupInfo":"","HasLabel":-1,"LabelID":0}},
{"type":"Feature","geometry":{"type":"Point","coordinates":[5.92097700000005,50.057044000000076,0,-1.7976931348623157e+308]},"properties":{"Name":"9th AD","FolderPath":"1945-01-18T00:00:01Z","SymbolID":15,"AltMode":-1,"Base":0,"TimeSpan":0,"TimeStamp":0,"BeginTime":"","EndTime":"","Snippet":"","PopupInfo":"","HasLabel":-1,"LabelID":0}},
{"type":"Feature","geometry":{"type":"Point","coordinates":[5.895099000000073,50.08670700000005,0,-1.7976931348623157e+308]},"properties":{"Name":"26th ID","FolderPath":"1945-01-18T00:00:01Z","SymbolID":13,"AltMode":-1,"Base":0,"TimeSpan":0,"TimeStamp":0,"BeginTime":"","EndTime":"","Snippet":"","PopupInfo":"","HasLabel":-1,"LabelID":0}},
{"type":"Feature","geometry":{"type":"Point","coordinates":[6.029723000000047,50.094790000000046,0,-1.7976931348623157e+308]},"properties":{"Name":"FE AD","FolderPath":"1945-01-18T00:00:01Z","SymbolID":15,"AltMode":-1,"Base":0,"TimeSpan":0,"TimeStamp":0,"BeginTime":"","EndTime":"","Snippet":"","PopupInfo":"","HasLabel":-1,"LabelID":0}},
{"type":"Feature","geometry":{"type":"Point","coordinates":[5.869869000000051,50.115117000000055,0,-1.7976931348623157e+308]},"properties":{"Name":"Lehr AD","FolderPath":"1945-01-18T00:00:01Z","SymbolID":15,"AltMode":-1,"Base":0,"TimeSpan":0,"TimeStamp":0,"BeginTime":"","EndTime":"","Snippet":"","PopupInfo":"","HasLabel":-1,"LabelID":0}},
{"type":"Feature","geometry":{"type":"Point","coordinates":[5.899015000000077,50.145114000000035,0,-1.7976931348623157e+308]},"properties":{"Name":"2nd AD","FolderPath":"1945-01-18T00:00:01Z","SymbolID":15,"AltMode":-1,"Base":0,"TimeSpan":0,"TimeStamp":0,"BeginTime":"","EndTime":"","Snippet":"","PopupInfo":"","HasLabel":-1,"LabelID":0}},
{"type":"Feature","geometry":{"type":"Point","coordinates":[5.94728200000003,50.171651000000054,0,-1.7976931348623157e+308]},"properties":{"Name":"116th AD","FolderPath":"1945-01-18T00:00:01Z","SymbolID":15,"AltMode":-1,"Base":0,"TimeSpan":0,"TimeStamp":0,"BeginTime":"","EndTime":"","Snippet":"","PopupInfo":"","HasLabel":-1,"LabelID":0}},
{"type":"Feature","geometry":{"type":"Point","coordinates":[5.976623000000075,50.20402000000007,0,-1.7976931348623157e+308]},"properties":{"Name":"2nd SS AD","FolderPath":"1945-01-18T00:00:01Z","SymbolID":15,"AltMode":-1,"Base":0,"TimeSpan":0,"TimeStamp":0,"BeginTime":"","EndTime":"","Snippet":"","PopupInfo":"","HasLabel":-1,"LabelID":0}},
{"type":"Feature","geometry":{"type":"Point","coordinates":[5.990549000000044,50.23293200000006,0,-1.7976931348623157e+308]},"properties":{"Name":"560th ID","FolderPath":"1945-01-18T00:00:01Z","SymbolID":13,"AltMode":-1,"Base":0,"TimeSpan":0,"TimeStamp":0,"BeginTime":"","EndTime":"","Snippet":"","PopupInfo":"","HasLabel":-1,"LabelID":0}},
{"type":"Feature","geometry":{"type":"Point","coordinates":[6.010696000000053,50.261442000000045,0,-1.7976931348623157e+308]},"properties":{"Name":"9th SS AD","FolderPath":"1945-01-18T00:00:01Z","SymbolID":15,"AltMode":-1,"Base":0,"TimeSpan":0,"TimeStamp":0,"BeginTime":"","EndTime":"","Snippet":"","PopupInfo":"","HasLabel":-1,"LabelID":0}},
{"type":"Feature","geometry":{"type":"Point","coordinates":[6.04079100000007,50.28213100000005,0,-1.7976931348623157e+308]},"properties":{"Name":"12th ID","FolderPath":"1945-01-18T00:00:01Z","SymbolID":13,"AltMode":-1,"Base":0,"TimeSpan":0,"TimeStamp":0,"BeginTime":"","EndTime":"","Snippet":"","PopupInfo":"","HasLabel":-1,"LabelID":0}},
{"type":"Feature","geometry":{"type":"Point","coordinates":[6.094563000000051,50.30734400000006,0,-1.7976931348623157e+308]},"properties":{"Name":"326th ID","FolderPath":"1945-01-18T00:00:01Z","SymbolID":13,"AltMode":-1,"Base":0,"TimeSpan":0,"TimeStamp":0,"BeginTime":"","EndTime":"","Snippet":"","PopupInfo":"","HasLabel":-1,"LabelID":0}},
{"type":"Feature","geometry":{"type":"Point","coordinates":[6.1611050000000205,50.26411900000005,0,-1.7976931348623157e+308]},"properties":{"Name":"62nd ID","FolderPath":"1945-01-18T00:00:01Z","SymbolID":13,"AltMode":-1,"Base":0,"TimeSpan":0,"TimeStamp":0,"BeginTime":"","EndTime":"","Snippet":"","PopupInfo":"","HasLabel":-1,"LabelID":0}},
{"type":"Feature","geometry":{"type":"Point","coordinates":[6.1777830000000336,50.32993300000004,0,-1.7976931348623157e+308]},"properties":{"Name":"18th ID","FolderPath":"1945-01-18T00:00:01Z","SymbolID":13,"AltMode":-1,"Base":0,"TimeSpan":0,"TimeStamp":0,"BeginTime":"","EndTime":"","Snippet":"","PopupInfo":"","HasLabel":-1,"LabelID":0}},
{"type":"Feature","geometry":{"type":"Point","coordinates":[6.243614000000036,50.35497000000004,0,-1.7976931348623157e+308]},"properties":{"Name":"3rd AirD","FolderPath":"1945-01-18T00:00:01Z","SymbolID":14,"AltMode":-1,"Base":0,"TimeSpan":0,"TimeStamp":0,"BeginTime":"","EndTime":"","Snippet":"","PopupInfo":"","HasLabel":-1,"LabelID":0}},
{"type":"Feature","geometry":{"type":"Point","coordinates":[6.361724000000038,50.36216500000006,0,-1.7976931348623157e+308]},"properties":{"Name":"89th ID","FolderPath":"1945-01-18T00:00:01Z","SymbolID":13,"AltMode":-1,"Base":0,"TimeSpan":0,"TimeStamp":0,"BeginTime":"","EndTime":"","Snippet":"","PopupInfo":"","HasLabel":-1,"LabelID":0}},
{"type":"Feature","geometry":{"type":"Point","coordinates":[6.385256000000027,50.410555000000045,0,-1.7976931348623157e+308]},"properties":{"Name":"277th ID","FolderPath":"1945-01-18T00:00:01Z","SymbolID":13,"AltMode":-1,"Base":0,"TimeSpan":0,"TimeStamp":0,"BeginTime":"","EndTime":"","Snippet":"","PopupInfo":"","HasLabel":-1,"LabelID":0}},
{"type":"Feature","geometry":{"type":"Point","coordinates":[6.210376000000053,49.888911000000064,0,-1.7976931348623157e+308]},"properties":{"Name":"79th ID","FolderPath":"1945-01-18T00:00:01Z","SymbolID":13,"AltMode":-1,"Base":0,"TimeSpan":0,"TimeStamp":0,"BeginTime":"","EndTime":"","Snippet":"","PopupInfo":"","HasLabel":-1,"LabelID":0}},
{"type":"Feature","geometry":{"type":"Point","coordinates":[6.311577000000057,49.88577200000003,0,-1.7976931348623157e+308]},"properties":{"Name":"352nd ID","FolderPath":"1945-01-18T00:00:01Z","SymbolID":13,"AltMode":-1,"Base":0,"TimeSpan":0,"TimeStamp":0,"BeginTime":"","EndTime":"","Snippet":"","PopupInfo":"","HasLabel":-1,"LabelID":0}},
{"type":"Feature","geometry":{"type":"Point","coordinates":[6.611579000000063,49.79026200000004,0,-1.7976931348623157e+308]},"properties":{"Name":"212th ID","FolderPath":"1945-01-18T00:00:01Z","SymbolID":13,"AltMode":-1,"Base":0,"TimeSpan":0,"TimeStamp":0,"BeginTime":"","EndTime":"","Snippet":"","PopupInfo":"","HasLabel":-1,"LabelID":0}},
{"type":"Feature","geometry":{"type":"Point","coordinates":[6.517210000000034,49.52105800000004,0,-1.7976931348623157e+308]},"properties":{"Name":"416th ID","FolderPath":"1945-01-18T00:00:01Z","SymbolID":13,"AltMode":-1,"Base":0,"TimeSpan":0,"TimeStamp":0,"BeginTime":"","EndTime":"","Snippet":"","PopupInfo":"","HasLabel":-1,"LabelID":0}},
{"type":"Feature","geometry":{"type":"Point","coordinates":[6.701668000000041,49.64506600000004,0,-1.7976931348623157e+308]},"properties":{"Name":"11th AD (2)","FolderPath":"1945-01-18T00:00:01Z","SymbolID":15,"AltMode":-1,"Base":0,"TimeSpan":0,"TimeStamp":0,"BeginTime":"","EndTime":"","Snippet":"","PopupInfo":"","HasLabel":-1,"LabelID":0}},
{"type":"Feature","geometry":{"type":"Point","coordinates":[6.44963000000007,49.555878000000064,0,-1.7976931348623157e+308]},"properties":{"Name":"11th AD","FolderPath":"1945-01-18T00:00:01Z","SymbolID":15,"AltMode":-1,"Base":0,"TimeSpan":0,"TimeStamp":0,"BeginTime":"","EndTime":"","Snippet":"","PopupInfo":"","HasLabel":-1,"LabelID":0}},
{"type":"Feature","geometry":{"type":"Point","coordinates":[6.814133000000027,49.45523700000007,0,-1.7976931348623157e+308]},"properties":{"Name":"719th ID","FolderPath":"1945-01-18T00:00:01Z","SymbolID":13,"AltMode":-1,"Base":0,"TimeSpan":0,"TimeStamp":0,"BeginTime":"","EndTime":"","Snippet":"","PopupInfo":"","HasLabel":-1,"LabelID":0}},
{"type":"Feature","geometry":{"type":"Point","coordinates":[7.5959510000000705,49.47258800000003,0,-1.7976931348623157e+308]},"properties":{"Name":"10th SS ID","FolderPath":"1945-01-18T00:00:01Z","SymbolID":13,"AltMode":-1,"Base":0,"TimeSpan":0,"TimeStamp":0,"BeginTime":"","EndTime":"","Snippet":"","PopupInfo":"","HasLabel":-1,"LabelID":0}},
{"type":"Feature","geometry":{"type":"Point","coordinates":[7.390696000000048,49.33513000000005,0,-1.7976931348623157e+308]},"properties":{"Name":"172nd ID","FolderPath":"1945-01-18T00:00:01Z","SymbolID":13,"AltMode":-1,"Base":0,"TimeSpan":0,"TimeStamp":0,"BeginTime":"","EndTime":"","Snippet":"","PopupInfo":"","HasLabel":-1,"LabelID":0}},
{"type":"Feature","geometry":{"type":"Point","coordinates":[6.933089000000052,49.28532000000007,0,-1.7976931348623157e+308]},"properties":{"Name":"347th ID","FolderPath":"1945-01-18T00:00:01Z","SymbolID":13,"AltMode":-1,"Base":0,"TimeSpan":0,"TimeStamp":0,"BeginTime":"","EndTime":"","Snippet":"","PopupInfo":"","HasLabel":-1,"LabelID":0}},
{"type":"Feature","geometry":{"type":"Point","coordinates":[7.082479000000035,49.22288800000007,0,-1.7976931348623157e+308]},"properties":{"Name":"19th ID","FolderPath":"1945-01-18T00:00:01Z","SymbolID":13,"AltMode":-1,"Base":0,"TimeSpan":0,"TimeStamp":0,"BeginTime":"","EndTime":"","Snippet":"","PopupInfo":"","HasLabel":-1,"LabelID":0}},
{"type":"Feature","geometry":{"type":"Point","coordinates":[7.554164000000071,49.20814400000006,0,-1.7976931348623157e+308]},"properties":{"Name":"6th SS ID","FolderPath":"1945-01-18T00:00:01Z","SymbolID":13,"AltMode":-1,"Base":0,"TimeSpan":0,"TimeStamp":0,"BeginTime":"","EndTime":"","Snippet":"","PopupInfo":"","HasLabel":-1,"LabelID":0}},
{"type":"Feature","geometry":{"type":"Point","coordinates":[7.5540110000000595,49.24139000000008,0,-1.7976931348623157e+308]},"properties":{"Name":"361st ID","FolderPath":"1945-01-18T00:00:01Z","SymbolID":13,"AltMode":-1,"Base":0,"TimeSpan":0,"TimeStamp":0,"BeginTime":"","EndTime":"","Snippet":"","PopupInfo":"","HasLabel":-1,"LabelID":0}},
{"type":"Feature","geometry":{"type":"Point","coordinates":[7.2444940000000315,49.13059000000004,0,-1.7976931348623157e+308]},"properties":{"Name":"17th SS ID","FolderPath":"1945-01-18T00:00:01Z","SymbolID":13,"AltMode":-1,"Base":0,"TimeSpan":0,"TimeStamp":0,"BeginTime":"","EndTime":"","Snippet":"","PopupInfo":"","HasLabel":-1,"LabelID":0}},
{"type":"Feature","geometry":{"type":"Point","coordinates":[7.418683000000044,49.05206500000003,0,-1.7976931348623157e+308]},"properties":{"Name":"559th ID","FolderPath":"1945-01-18T00:00:01Z","SymbolID":13,"AltMode":-1,"Base":0,"TimeSpan":0,"TimeStamp":0,"BeginTime":"","EndTime":"","Snippet":"","PopupInfo":"","HasLabel":-1,"LabelID":0}},
{"type":"Feature","geometry":{"type":"Point","coordinates":[7.397143000000028,48.971831000000066,0,-1.7976931348623157e+308]},"properties":{"Name":"257th ID","FolderPath":"1945-01-18T00:00:01Z","SymbolID":13,"AltMode":-1,"Base":0,"TimeSpan":0,"TimeStamp":0,"BeginTime":"","EndTime":"","Snippet":"","PopupInfo":"","HasLabel":-1,"LabelID":0}},
{"type":"Feature","geometry":{"type":"Point","coordinates":[7.4853010000000495,48.99605800000006,0,-1.7976931348623157e+308]},"properties":{"Name":"256th ID","FolderPath":"1945-01-18T00:00:01Z","SymbolID":13,"AltMode":-1,"Base":0,"TimeSpan":0,"TimeStamp":0,"BeginTime":"","EndTime":"","Snippet":"","PopupInfo":"","HasLabel":-1,"LabelID":0}},
{"type":"Feature","geometry":{"type":"Point","coordinates":[7.616066000000046,48.99976200000003,0,-1.7976931348623157e+308]},"properties":{"Name":"36th ID","FolderPath":"1945-01-18T00:00:01Z","SymbolID":13,"AltMode":-1,"Base":0,"TimeSpan":0,"TimeStamp":0,"BeginTime":"","EndTime":"","Snippet":"","PopupInfo":"","HasLabel":-1,"LabelID":0}},
{"type":"Feature","geometry":{"type":"Point","coordinates":[7.791748000000041,49.013505000000066,0,-1.7976931348623157e+308]},"properties":{"Name":"245th ID","FolderPath":"1945-01-18T00:00:01Z","SymbolID":13,"AltMode":-1,"Base":0,"TimeSpan":0,"TimeStamp":0,"BeginTime":"","EndTime":"","Snippet":"","PopupInfo":"","HasLabel":-1,"LabelID":0}},
{"type":"Feature","geometry":{"type":"Point","coordinates":[7.964182000000051,49.00366200000008,0,-1.7976931348623157e+308]},"properties":{"Name":"121st AD","FolderPath":"1945-01-18T00:00:01Z","SymbolID":15,"AltMode":-1,"Base":0,"TimeSpan":0,"TimeStamp":0,"BeginTime":"","EndTime":"","Snippet":"","PopupInfo":"","HasLabel":-1,"LabelID":0}},
{"type":"Feature","geometry":{"type":"Point","coordinates":[8.508955000000071,48.95937100000003,0,-1.7976931348623157e+308]},"properties":{"Name":"216th ID (?)","FolderPath":"1945-01-18T00:00:01Z","SymbolID":13,"AltMode":-1,"Base":0,"TimeSpan":0,"TimeStamp":0,"BeginTime":"","EndTime":"","Snippet":"","PopupInfo":"","HasLabel":-1,"LabelID":0}},
{"type":"Feature","geometry":{"type":"Point","coordinates":[8.031620000000032,48.90939100000003,0,-1.7976931348623157e+308]},"properties":{"Name":"7th AirD","FolderPath":"1945-01-18T00:00:01Z","SymbolID":14,"AltMode":-1,"Base":0,"TimeSpan":0,"TimeStamp":0,"BeginTime":"","EndTime":"","Snippet":"","PopupInfo":"","HasLabel":-1,"LabelID":0}},
{"type":"Feature","geometry":{"type":"Point","coordinates":[8.053985000000068,48.831206000000066,0,-1.7976931348623157e+308]},"properties":{"Name":"28th ID","FolderPath":"1945-01-18T00:00:01Z","SymbolID":13,"AltMode":-1,"Base":0,"TimeSpan":0,"TimeStamp":0,"BeginTime":"","EndTime":"","Snippet":"","PopupInfo":"","HasLabel":-1,"LabelID":0}},
{"type":"Feature","geometry":{"type":"Point","coordinates":[7.919349000000068,48.67964200000006,0,-1.7976931348623157e+308]},"properties":{"Name":"553rd ID","FolderPath":"1945-01-18T00:00:01Z","SymbolID":13,"AltMode":-1,"Base":0,"TimeSpan":0,"TimeStamp":0,"BeginTime":"","EndTime":"","Snippet":"","PopupInfo":"","HasLabel":-1,"LabelID":0}},
{"type":"Feature","geometry":{"type":"Point","coordinates":[8.070283000000074,48.35754500000007,0,-1.7976931348623157e+308]},"properties":{"Name":"405th ID","FolderPath":"1945-01-18T00:00:01Z","SymbolID":13,"AltMode":-1,"Base":0,"TimeSpan":0,"TimeStamp":0,"BeginTime":"","EndTime":"","Snippet":"","PopupInfo":"","HasLabel":-1,"LabelID":0}},
{"type":"Feature","geometry":{"type":"Point","coordinates":[7.592245000000048,48.28044500000004,0,-1.7976931348623157e+308]},"properties":{"Name":"106th AD","FolderPath":"1945-01-18T00:00:01Z","SymbolID":15,"AltMode":-1,"Base":0,"TimeSpan":0,"TimeStamp":0,"BeginTime":"","EndTime":"","Snippet":"","PopupInfo":"","HasLabel":-1,"LabelID":0}},
{"type":"Feature","geometry":{"type":"Point","coordinates":[7.688298000000032,48.34288500000008,0,-1.7976931348623157e+308]},"properties":{"Name":"196th ID","FolderPath":"1945-01-18T00:00:01Z","SymbolID":13,"AltMode":-1,"Base":0,"TimeSpan":0,"TimeStamp":0,"BeginTime":"","EndTime":"","Snippet":"","PopupInfo":"","HasLabel":-1,"LabelID":0}},
{"type":"Feature","geometry":{"type":"Point","coordinates":[7.531362000000058,48.21858100000003,0,-1.7976931348623157e+308]},"properties":{"Name":"269th ID","FolderPath":"1945-01-18T00:00:01Z","SymbolID":13,"AltMode":-1,"Base":0,"TimeSpan":0,"TimeStamp":0,"BeginTime":"","EndTime":"","Snippet":"","PopupInfo":"","HasLabel":-1,"LabelID":0}},
{"type":"Feature","geometry":{"type":"Point","coordinates":[7.376135000000033,48.07506600000005,0,-1.7976931348623157e+308]},"properties":{"Name":"189th ID","FolderPath":"1945-01-18T00:00:01Z","SymbolID":13,"AltMode":-1,"Base":0,"TimeSpan":0,"TimeStamp":0,"BeginTime":"","EndTime":"","Snippet":"","PopupInfo":"","HasLabel":-1,"LabelID":0}},
{"type":"Feature","geometry":{"type":"Point","coordinates":[7.464038000000073,48.12297200000006,0,-1.7976931348623157e+308]},"properties":{"Name":"708th ID","FolderPath":"1945-01-18T00:00:01Z","SymbolID":13,"AltMode":-1,"Base":0,"TimeSpan":0,"TimeStamp":0,"BeginTime":"","EndTime":"","Snippet":"","PopupInfo":"","HasLabel":-1,"LabelID":0}},
{"type":"Feature","geometry":{"type":"Point","coordinates":[7.675330000000031,48.05157100000008,0,-1.7976931348623157e+308]},"properties":{"Name":"30th SS ID","FolderPath":"1945-01-18T00:00:01Z","SymbolID":13,"AltMode":-1,"Base":0,"TimeSpan":0,"TimeStamp":0,"BeginTime":"","EndTime":"","Snippet":"","PopupInfo":"","HasLabel":-1,"LabelID":0}},
{"type":"Feature","geometry":{"type":"Point","coordinates":[7.524348000000032,48.00794600000006,0,-1.7976931348623157e+308]},"properties":{"Name":"716th ID","FolderPath":"1945-01-18T00:00:01Z","SymbolID":13,"AltMode":-1,"Base":0,"TimeSpan":0,"TimeStamp":0,"BeginTime":"","EndTime":"","Snippet":"","PopupInfo":"","HasLabel":-1,"LabelID":0}},
{"type":"Feature","geometry":{"type":"Point","coordinates":[7.302577000000042,48.006552000000056,0,-1.7976931348623157e+308]},"properties":{"Name":"159th ID","FolderPath":"1945-01-18T00:00:01Z","SymbolID":13,"AltMode":-1,"Base":0,"TimeSpan":0,"TimeStamp":0,"BeginTime":"","EndTime":"","Snippet":"","PopupInfo":"","HasLabel":-1,"LabelID":0}}
]}